<?xml version="1.0" encoding="UTF-8"?>
<LanguageData>
  
  <!-- EN: Cancel -->
  <DesignatorCancel>キャンセル</DesignatorCancel>
  <!-- EN: Cancel designated building, mining, hauling, harvesting, and all other designations. -->
  <DesignatorCancelDesc>建物の作成,採掘,アイテムの運搬,食材の収穫など 指示したことを中止します.</DesignatorCancelDesc>

  <!-- EN: Cut plants -->
  <DesignatorCutPlants>刈り取り</DesignatorCutPlants>
  <!-- EN: Marks plants to be cut and destroyed. The plant will be completely removed, and any food or resource yield will be harvested. -->
  <DesignatorCutPlantsDesc>植物を刈り取るために 印をつけます.植物は完全に取り除かれ, それが 食材や資源であれば 収穫されます.</DesignatorCutPlantsDesc>

  <!-- EN: Deconstruct -->
  <DesignatorDeconstruct>解体</DesignatorDeconstruct>
  <!-- EN: Deconstruct this and reclaim part of its resources. -->
  <DesignatorDeconstructDesc>建物を解体し, その材料の 一部を 再利用します.</DesignatorDeconstructDesc>

  <!-- EN: Uninstall -->
  <DesignatorUninstall>撤去</DesignatorUninstall>
  <!-- EN: Uninstall this so it can be moved, sold, or installed somewhere else. -->
  <DesignatorUninstallDesc>移設,売却,別の場所に再展示するために 撤去します.</DesignatorUninstallDesc>

  <!-- EN: Harvest -->
  <DesignatorHarvest>収穫</DesignatorHarvest>
  <!-- EN: Marks plants to be harvested for their food or other products. -->
  <DesignatorHarvestDesc>食料や 他の製品にするために 収穫する印をつけます.</DesignatorHarvestDesc>

  <!-- EN: Chop wood -->
  <DesignatorHarvestWood>伐採</DesignatorHarvestWood>
  <!-- EN: Marks trees to be chopped down for wood. -->
  <DesignatorHarvestWoodDesc>木を 切り倒し木材にするために 印をつけます.</DesignatorHarvestWoodDesc>

  <!-- EN: Haul things -->
  <DesignatorHaulThings>運搬</DesignatorHaulThings>
  <!-- EN: Mark rock chunks and other items to be hauled to dumping areas. Not needed for things like food or corpses, which are always haulable. -->
  <DesignatorHaulThingsDesc>岩の塊や その他のアイテムを廃棄ゾーンに運ぶために 印をつけます. 食材や死体といったものに印をつける必要はありません それらは自動的に運ばれます.</DesignatorHaulThingsDesc>
  <!-- EN: Can only designate haulable but non-always-hauled things (like rock chunks). -->
  <MustHaulHaulables>自動で運ぶもの以外の,アイテムだけを指定することができます(岩の塊など) .</MustHaulHaulables>

  <!-- EN: Hunt -->
  <DesignatorHunt>狩猟</DesignatorHunt>
  <!-- EN: Mark animals to be hunted by your hunters. -->
  <DesignatorHuntDesc>動物を狩るために 狙いをつけます.</DesignatorHuntDesc>

  <!-- EN: Mine -->
  <DesignatorMine>採掘</DesignatorMine>
  <!-- EN: Designate areas of rock to be mined out. -->
  <DesignatorMineDesc>採掘するために ゾーンを指示します.</DesignatorMineDesc>

  <!-- EN: Smooth surface -->
  <DesignatorSmoothSurface>表面を磨く</DesignatorSmoothSurface>
  <!-- EN: Designate rough stone terrain and walls to be smoothed. -->
  <DesignatorSmoothSurfaceDesc>荒削りの岩の 床や壁を磨かせるために 印をつけます.</DesignatorSmoothSurfaceDesc>

  <!-- EN: Plan -->
  <DesignatorPlan>予定地</DesignatorPlan>
  <!-- EN: Place planning designations. These don't do anything except help you plan future expansions. -->
  <DesignatorPlanDesc>予定地を 設定します. 予定地として 印をつける のみで 実際には なにもしません.</DesignatorPlanDesc>

  <!-- EN: Remove plans -->
  <DesignatorPlanRemove>予定地を 取り消す</DesignatorPlanRemove>
  <!-- EN: Remove planning designations. -->
  <DesignatorPlanRemoveDesc>予定地を 取り消します.</DesignatorPlanRemoveDesc>

  <!-- EN: Forbid -->
  <DesignatorForbid>禁止</DesignatorForbid>
  <!-- EN: Mark items as forbidden. Colonists will not be able to interact with the designated items. -->
  <DesignatorForbidDesc>接触禁止と 印をつけます.入植者は指示されたアイテムに作用することができなくなります.</DesignatorForbidDesc>

  <!-- EN: Allow -->
  <DesignatorUnforbid>許可</DesignatorUnforbid>
  <!-- EN: Mark items as not forbidden. Colonists will be able to interact with the designated items. -->
  <DesignatorUnforbidDesc>接触禁止の印を 解除します.入植者は指示されたアイテムに作用することができるようになります</DesignatorUnforbidDesc>

  <!-- EN: Expand home area -->
  <DesignatorAreaHomeExpand>コロニーゾーン</DesignatorAreaHomeExpand>
  <!-- EN: Colonists will repair buildings, clean floors, and extinguish fires only in the home area. -->
  <DesignatorAreaHomeExpandDesc>入植者は コロニーゾーン内だけの 建物を修理し, 床を掃除し,火災を消そうとします.</DesignatorAreaHomeExpandDesc>
  <!-- EN: Clear home area -->
  <DesignatorAreaHomeClear>コロニーゾーン 取消</DesignatorAreaHomeClear>
  <!-- EN: Removes a home area. Colonists will no longer clean, repair, or extinguish fires here. -->
  <DesignatorAreaHomeClearDesc>コロニーゾーンを 取り消します. 取り消された場所を, 入植者が 修理したり, 掃除したり, 火災を消そうとはしなくなります.</DesignatorAreaHomeClearDesc>

  <!-- EN: Build roof area -->
  <DesignatorAreaBuildRoofExpand>屋根ゾーン</DesignatorAreaBuildRoofExpand>
  <!-- EN: Colonists will build roofs in this area. -->
  <DesignatorAreaBuildRoofExpandDesc>屋根を 作成する ゾーンを 指定します.</DesignatorAreaBuildRoofExpandDesc>

  <!-- EN: Remove roof area -->
  <DesignatorAreaNoRoofExpand>屋根取り外し</DesignatorAreaNoRoofExpand>
  <!-- EN: Colonists will remove roofs in this area (except overhead mountain, which cannot be removed). -->
  <DesignatorAreaNoRoofExpandDesc>屋根を 作成しない ゾーンを 指定します. 既存の 屋根が ある時は, 入植者が 屋根を とりはずします(頭上に山がある場合は とりはずせません).</DesignatorAreaNoRoofExpandDesc>

  <!-- EN: Ignore roof area -->
  <DesignatorAreaIgnoreRoofExpand>屋根の無視ゾーン</DesignatorAreaIgnoreRoofExpand>
  <!-- EN: Colonists will ignore roofs in this area. -->
  <DesignatorAreaIgnoreRoofExpandDesc>入植者は このゾーンの 屋根を 無視するでしょう.</DesignatorAreaIgnoreRoofExpandDesc>

  <!-- EN: Expand snow clear area -->
  <DesignatorAreaSnowClearExpand>除雪ゾーン</DesignatorAreaSnowClearExpand>
  <!-- EN: Create a area which colonists will try to keep clear of snow. -->
  <DesignatorAreaSnowClearExpandDesc>入植者が雪かきする場所を指定します.</DesignatorAreaSnowClearExpandDesc>
  <!-- EN: Clear snow clear Area -->
  <DesignatorAreaSnowClearClear>除雪ゾーン 取消</DesignatorAreaSnowClearClear>
  <!-- EN: Removes a snow clearing area. Colonists will no longer try to keep this area clear of snow. -->
  <DesignatorAreaSnowClearClearDesc>雪かきする場所の指定を取り消します.もうそこを入植者は雪かきしません.</DesignatorAreaSnowClearClearDesc>

  <!-- EN: Expand allowed area -->
  <DesignatorExpandAreaAllowed>制限ゾーン</DesignatorExpandAreaAllowed>
  <!-- EN: Expand an allowed area.\n\nAllowed areas are defined areas you can assign to colonists. Colonists will not accept work or fulfill their needs outside their allowed area. -->
  <DesignatorExpandAreaAllowedDesc>制限ゾーンを広げます.\n\n制限ゾーンとは,入植者を 割り当てることができる ゾーンとして定義されました.入植者は 彼に割り当てられた 制限ゾーンの外側では 作業を受付しませんし, 必要と思われる作業も遂行しません.</DesignatorExpandAreaAllowedDesc>
  <!-- EN: Clear allowed area -->
  <DesignatorClearAreaAllowed>制限ゾーン 取消</DesignatorClearAreaAllowed>
  <!-- EN: Clear cells from an allowed area.\n\nAllowed area are defined areas you can assign to colonists. Colonists will not accept work or fulfill their needs outside their allowed area. -->
  <DesignatorClearAreaAllowedDesc>制限ゾーンを 取り消します.</DesignatorClearAreaAllowedDesc>
  <!-- EN: Manage areas... -->
  <ManageAreas>制限ゾーンの管理...</ManageAreas>

  <!-- EN: Create a zone where your colonists will try to grow a certain kind of plant. -->
  <DesignatorGrowingZoneDesc>入植者が ある種の植物を 栽培しようとするための ゾーンを作成します.</DesignatorGrowingZoneDesc>

  <!-- EN: Create a stockpile where your colonists will store resources.\nThis tool can also expand any existing stockpile. -->
  <DesignatorZoneCreateStorageResourcesDesc>入植者が 材料を 備蓄する場所を 作成します.\nこのツールは, すでにある備蓄ゾーンを 拡張することも できます.</DesignatorZoneCreateStorageResourcesDesc>

  <!-- EN: Create a stockpile where your colonists will store junk.\nThis tool can also expand any existing stockpile. -->
  <DesignatorZoneCreateStorageDumpingDesc>入植者が ゴミを 捨てる場所を 作成します.\nこのツールは, すでにある廃棄ゾーンを 拡張することも できます.</DesignatorZoneCreateStorageDumpingDesc>

  <!-- EN: Shrink zones -->
  <DesignatorZoneDelete>ゾーン取消</DesignatorZoneDelete>
  <!-- EN: Shrink zone -->
  <DesignatorZoneDeleteSingular>ゾーン取消</DesignatorZoneDeleteSingular>
  <!-- EN: Remove zones, like stockpile zones or growing zones. -->
  <DesignatorZoneDeleteDesc>備蓄ゾーン, 廃棄ゾーン, または 農業ゾーンを 取り消します.</DesignatorZoneDeleteDesc>

  <!-- EN: Expand zone -->
  <DesignatorZoneExpand>ゾーン拡張</DesignatorZoneExpand>
  
  <!-- EN: Claim -->
  <DesignatorClaim>領有を主張</DesignatorClaim>
  <!-- EN: Claim neutral structures for the colony, including ancient ruins and abandoned siege bases. Claimed structures can be repaired and maintained by your colonists. -->
  <DesignatorClaimDesc>中立の構造物(遺跡や放棄された基地)の領有を主張します.こうすることで,入植者は 構造物の修理や維持を行うことができます.</DesignatorClaimDesc>

  <!-- EN: Remove floor -->
  <DesignatorRemoveFloor>フロアを除去</DesignatorRemoveFloor>
  <!-- EN: Remove floors to reveal the terrain underneath. -->
  <DesignatorRemoveFloorDesc>床を剥がして地面を出します.</DesignatorRemoveFloorDesc>

  <!-- EN: Remove bridge -->
  <DesignatorRemoveBridge>橋梁解体</DesignatorRemoveBridge>
  <!-- EN: Remove bridges to reveal the terrain underneath. -->
  <DesignatorRemoveBridgeDesc>橋梁を解体して,下の地形を露出させます.</DesignatorRemoveBridgeDesc>

  <!-- EN: Strip -->
  <DesignatorStrip>剥ぐ</DesignatorStrip>
  <!-- EN: Strip apparel from corpses and the wounded. -->
  <DesignatorStripDesc>死体や,けが人から 衣服を剥がします.</DesignatorStripDesc>

  <!-- EN: Open -->
  <DesignatorOpen>開ける</DesignatorOpen>
  <!-- EN: Open containers. -->
  <DesignatorOpenDesc>箱を開けます.</DesignatorOpenDesc>
  
  <!-- EN: Slaughter -->
  <DesignatorSlaughter>屠殺</DesignatorSlaughter>
  <!-- EN: Slaughter a tame animal. -->
  <DesignatorSlaughterDesc>家畜を屠殺します.</DesignatorSlaughterDesc>

  <!-- EN: Tame -->
  <DesignatorTame>手なずける</DesignatorTame>
  <!-- EN: Tame a wild animal. -->
  <DesignatorTameDesc>野生動物を手なずけます.</DesignatorTameDesc>

  <!-- Failure messages -->
  <!-- EN: Unchosen material -->
  <UnchosenStuff>素材が選ばれていません.</UnchosenStuff>
  <!-- EN: Too close to map edge. -->
  <TooCloseToMapEdge>マップ端に近すぎます.</TooCloseToMapEdge>
  <!-- EN: Out of bounds. -->
  <OutOfBounds>領域外です.</OutOfBounds>
  <!-- EN: Cannot place in undiscovered areas. -->
  <CannotPlaceInUndiscovered>未知の場所に配置することはできません.</CannotPlaceInUndiscovered>
  <!-- EN: Interaction spot is blocked by {1_labelShort}. -->
  <InteractionSpotBlocked>{1_labelShort}によって 作用空間がブロックされています.</InteractionSpotBlocked>
  <!-- EN: Interaction spot is out of bounds. -->
  <InteractionSpotOutOfBounds>作用空間が 領域外です.</InteractionSpotOutOfBounds>
  <!-- EN: Interaction spot will be blocked by {1_labelShort}. -->
  <InteractionSpotWillBeBlocked>{1_labelShort}によって 作用空間が ブロックされるでしょう.</InteractionSpotWillBeBlocked>
  <!-- EN: {0} would block {1}'s interaction spot. -->
  <WouldBlockInteractionSpot>{0}が {1}の作用空間を ブロックするでしょう.</WouldBlockInteractionSpot>
  <!-- EN: The terrain here is already {0}. -->
  <TerrainIsAlready>すでにここの地形は {0} です.</TerrainIsAlready>
  <!-- EN: The surface is already marked for smoothing. -->
  <SurfaceBeingSmoothed>すでにこの表面は磨くよう指示されています.</SurfaceBeingSmoothed>
  <!-- EN: Identical thing already exists here. -->
  <IdenticalThingExists>すでに同じ物があります.</IdenticalThingExists>
  <!-- EN: Identical blueprint already exists here. -->
  <IdenticalBlueprintExists>すでに同じ設計図があります.</IdenticalBlueprintExists>
  <!-- EN: {0_label} cannot be built on this terrain. -->
  <TerrainCannotSupport>この地形の上には {0_label}を 建てることが できません.</TerrainCannotSupport>
  <!-- EN: {0_label} requires terrain that supports: {1_label} -->
  <TerrainCannotSupport_TerrainAffordance>{0_label}には,次の支持地盤が必要です: {1_label}</TerrainCannotSupport_TerrainAffordance>
  <!-- EN: {0_label} (when made of {2_label}) requires terrain that supports: {1_label} -->
  <TerrainCannotSupport_TerrainAffordanceFromStuff>{2_label}製{0_label}の支持地盤が必要です: {1_label}</TerrainCannotSupport_TerrainAffordanceFromStuff>
  <!-- EN: Space already occupied. -->
  <SpaceAlreadyOccupied>すでにこの場所は塞がっています.</SpaceAlreadyOccupied>
  <!-- EN: Space being smoothed. -->
  <SpaceBeingSmoothed>すでに磨くように指示されてます.</SpaceBeingSmoothed>
  <!-- EN: Must target a removable floor. -->
  <TerrainMustBeRemovable>剥がせるフロアを指定してください.</TerrainMustBeRemovable>
  <!-- EN: The waterwheel must be on moving water. -->
  <MustBeOnMovingWater>水車は流水に設置しなければなりません.</MustBeOnMovingWater>
  <!-- EN: Interaction spot will overlap with the interaction spot of {1_labelShort}. -->
  <InteractionSpotWillOverlap>作用空間が{1_labelShort}の作用空間と干渉しそうです.</InteractionSpotWillOverlap>
  <!-- EN: Interaction spot overlaps with the interaction spot of {1_labelShort}. -->
  <InteractionSpotOverlaps>作用空間が{1_labelShort}の作用空間と干渉しています.</InteractionSpotOverlaps>
  <!-- EN: Cannot place monument over: {0}. -->
  <CannotPlaceMonumentOver>モニュメントを設置できません: {0}</CannotPlaceMonumentOver>
  <!-- EN: Cannot build on: {0}. -->
  <CannotPlaceMonumentOnTerrain>建築できません: {0}</CannotPlaceMonumentOnTerrain>
  <!-- EN: Cannot place monument over: {0}. -->
  <MonumentOverlapsBuilding>モニュメントを設置できません: {0}</MonumentOverlapsBuilding>
  <!-- EN: Monument cannot be placed adjacent to: {0}. -->
  <MonumentAdjacentToBuilding>モニュメントは隣接して設置できません: {0}</MonumentAdjacentToBuilding>
  
  <!-- Mouse attachments -->
  <!-- EN: Expand {0} or\nCreate new {1} -->
  <ExpandOrCreateZone>{0}を拡張するか\n新しく{1}を作ります.</ExpandOrCreateZone>
  <!-- EN: Create new {0} -->
  <CreateNewZone>新しく{0}を作ります.</CreateNewZone>
  
  <!-- Desc helpers -->
  <!-- EN: Transmits power -->
  <TransmitsPower>送電します.</TransmitsPower>
  <!-- EN: Construction needed -->
  <ConstructionNeeded>建設が必要です.</ConstructionNeeded>
  <!-- EN: None of your {0} have this skill. -->
  <NoColonistWithSkillTip>このスキルを持っている{0}は一人もいません.</NoColonistWithSkillTip>
  <!-- EN: {0} needed -->
  <SkillNeededForConstructing>必要 {0}スキル</SkillNeededForConstructing>
  <!-- EN: None of your {0} have all skills required. -->
  <NoColonistWithAllSkillsForConstructing>{0}はひとりも必要なスキルを持っていません.</NoColonistWithAllSkillsForConstructing>
  <!-- EN: All of your {0} who have this skill are not assigned to {1}. -->
  <AllColonistsWithSkillHaveDisabledConstructingTip>このスキルを持っている全{0}が,{1}に割り当てられていません.</AllColonistsWithSkillHaveDisabledConstructingTip>

  <!-- UNUSED -->
  <MonumentBadTerrain>不適切な地盤の上にはモニュメントを設置できません.</MonumentBadTerrain>
  <MonumentBlockedPermanently>永続的な障害物の上にはモニュメントを設置できません.</MonumentBlockedPermanently>

</LanguageData>