<?xml version="1.0" encoding="UTF-8"?>
<LanguageData>

  <!-- Misc -->
  <!-- EN: Jump to location -->
  <JumpToLocation>その場所を見る</JumpToLocation>
  <!-- EN: Postpone -->
  <PostponeLetter>後回し</PostponeLetter>
  <!-- EN: Reject -->
  <RejectLetter>拒否</RejectLetter>
  <!-- EN: Read more -->
  <ReadMore>もっと読む</ReadMore>

  <!-- EN: Summer -->
  <LetterLabelFirstSummerWarning>夏の便り</LetterLabelFirstSummerWarning>
  <!-- EN: Summer has begun! But winter is coming.\n\nYour food crops won't grow in the winter cold. Be sure to store enough food to survive. You can build a walk-in refrigerator to prevent food from spoiling.\n\nBuy, steal, or make some parkas, or you'll freeze when you step outside. -->
  <FirstSummerWarning>夏が来た！でも直ぐに,冬もやってきます.\n\n作物は寒い冬の間は育ちません.食料を保存する準備をしましょう.\n\n冷凍庫となる部屋を造り,食料の腐敗を防ぐのです.\n\nパーカーを買うか,盗むか,作るかしておかないと,外に出た時に凍えてしまいます.</FirstSummerWarning>

  <!-- EN: Relations with {0} have broken down completely. They are now hostile to you.\n\nThey will conduct periodic raids on your colony and caravans, and refuse to trade with you. If you want to improve relations, you can still offer them gifts using caravans or transport pods.\n\nThis happened because goodwill ({1}) has fallen below {2}. In order to restore neutral relations, goodwill must reach {3} again. -->
  <LetterRelationsChange_Hostile>{0}との関係が断絶しました.彼らは今や敵です.\n\n彼らは,あなたのコロニーやキャラバン隊を定期的に襲撃するでしょう,さらにトレードを拒否します.あなたに関係改善の意思があるなら,キャラバン隊や輸送ポッドを使って,彼らに贈り物を申し出ることはできます.\n\nこれは友好値({1})が{2}以下の時に起きます.中立の関係に戻す目的なら,友好値を再び{3}に到達させなければなりません.</LetterRelationsChange_Hostile>
  <!-- EN: Relations with {0} have warmed. They now consider you neutral and will no longer attack you.\n\nThis happened because goodwill ({1}) has risen past {2}. If goodwill falls below {3}, {0} will become hostile again. If goodwill rises above {4}, they will become your ally and fight for you. -->
  <LetterRelationsChange_NeutralFromHostile>{0}との関係が改善しました.もう彼らは,あなたを攻撃しようともせず,中立とみなしています.\n\nこれは友好値({1})が{2}を超えれば発生します.もし友好値が{3}を下回れば,{0}は再び敵対します.もし友好値が{4}を上回れば,彼らはあなたと同盟を組み,あなたの為に戦うでしょう.</LetterRelationsChange_NeutralFromHostile>
  <!-- EN: Relations with {0} have cooled. They now consider you neutral instead of allied.\n\nWhile they will still interact peacefully with you, they will no longer send fighters to help you when you are under threat.\n\nThis happened because goodwill ({1}) has fallen below {2}. If goodwill falls below {3}, {0} will become hostile. If goodwill rises above {4}, they will become allied once again. -->
  <LetterRelationsChange_NeutralFromAlly>{0}との関係が冷え込みました.いまや彼らは,あなたを同盟ではなく中立とみなしています.\n\nあなたと円満な関係を続けますが,彼らは,貴方が脅威に晒されても援軍を送ってくることはありません.\n\nこれは友好値({1})が{2}を下回れば起きます.もし{3}を下回ると,{0}は敵対するでしょう.もし{4}を上回れば,彼らは再び,あなたと同盟を組むでしょう.</LetterRelationsChange_NeutralFromAlly>
  <!-- EN: Relations with {0} have become very close. They now consider you an ally.\n\nAllies will sometimes arrive to help fight your enemies when you are under attack. You can also call them for help at any time, at a cost of goodwill.\n\nYou've become allies because your goodwill ({1}) has risen past {2}. If goodwill falls below {3}, relations will return to neutral. -->
  <LetterRelationsChange_Ally>{0}との関係はとても緊密となりました.彼らは,あなたと同盟とみなしています.\n\n同盟を結ぶと,あなたが戦時下にあると,あなたの敵と戦う援軍が到着することがあります.あなたは,対価として友好値を費やすことで,いつでも彼らを呼び出すこともできます.\n\n友好値({1})が{2}を超えれば同盟となります.もし{3}を下回ると,関係は中立へと戻ります.</LetterRelationsChange_Ally>

  <!-- EN: goodwill -->
  <goodwill>友好</goodwill>
  <!-- EN: Neutral -->
  <Neutral>中立</Neutral>
  <!-- EN: Death -->
  <Death>死亡</Death>

  <!-- EN: A {1_label} has short-circuited in the rain and started a fire. -->
  <ShortCircuitRain>{1_label}は 雨で短絡し発火しました.</ShortCircuitRain>

  <!-- EN: Area revealed -->
  <LetterLabelAreaRevealed>発見</LetterLabelAreaRevealed>
  <!-- EN: A new area has been revealed. -->
  <AreaRevealed>新しいゾーンが明らかになりました.</AreaRevealed>
  <!-- EN: A new area has been revealed. It contains ancient, hostile mechanoids. -->
  <AreaRevealedWithMechanoids>新しいゾーンが明らかになりましたが,敵対する古代のメカノイドがいます.</AreaRevealedWithMechanoids>

  <!-- EN: A roof has collapsed because it was too far from any support. -->
  <RoofCollapsed>屋根の支えが遠すぎたため, 自重で崩落しました.</RoofCollapsed>
  <!-- EN: These things were crushed: -->
  <TheseThingsCrushed>崩落の被害</TheseThingsCrushed>
  <!-- EN: Nothing was crushed. -->
  <NothingCrushed>被害は ありませんでした.</NothingCrushed>
  <!-- EN: Roof collapse -->
  <LetterLabelRoofCollapsed>崩落</LetterLabelRoofCollapsed>

  <!-- EN: {0} successfully recruited {1} ({2} chance). -->
  <RecruitSuccess>{0}は {1}を コロニーに 迎え入れました. (成功率 {2})</RecruitSuccess>
  <!-- EN: {0} failed to recruit {1} ({2} chance). -->
  <RecruitFail>{0}は {1}の 説得に 失敗しました. (成功率 {2})</RecruitFail>

  <!-- EN: {PAWN_nameDef} is {RELATIVE_labelShort}'s {1}. If {PAWN_nameDef} dies, {RELATIVE_labelShort} will suffer from long-lasting grief. However, if you manage to rescue {PAWN_nameDef}, {RELATIVE_labelShort} will be very happy for a long time. -->
  <RelatedPawnInvolvedInQuest>{PAWN_nameDef}は {RELATIVE_labelShort}の{1}です.もし {PAWN_nameDef}が死ねば,{RELATIVE_labelShort}は,長期に渡る悲しみに苦しむでしょう.けれども,もしなんとか {PAWN_nameDef}を救うことができれば, {RELATIVE_labelShort}は,長い間,幸せに包まれているでしょう.</RelatedPawnInvolvedInQuest>

  <!-- EN: Birthday -->
  <LetterLabelBirthday>誕生日</LetterLabelBirthday>
  <!-- EN: It's {0}'s chronological birthday today! Biologically, {1} is {3} years old.\n\nChronologically, {1} just turned {2}.\n\nNote that since people don't age while in cryptosleep, chronological birthday is separate from biological birthday. -->
  <BirthdayChronological>今日は,{0}の誕生日です!,生物学的には {1}は {3}才になります.\n\n暦上では,{1}は,{2}になりました.\n\nノート:冷凍睡眠中は老化しないので,暦上の年齢は,生物学的年齢とは別になります.</BirthdayChronological>
  <!-- EN: {0_nameFull} has reached the biological age of {1}.\n\nUnfortunately, {0_nameFull} has gained the following diseases due to aging:\n{2} -->
  <BirthdayBiologicalAgeInjuries>今日は,{0}の 生物学的な {1}才の誕生日\n\nですが不幸にも 年齢からくる持病({2}) を悪くさせてしまいました.</BirthdayBiologicalAgeInjuries>

  <!-- EN: Disease -->
  <LetterLabelNewDisease>発症</LetterLabelNewDisease>
  <!-- EN: {PAWN} has gotten sick from {1}.\n\nEnsure you have a medical bed and a doctor. Make sure that {PAWN_definite} gets proper treatment and spends as much time in bed as possible. -->
  <NewDisease>{PAWN}は {1}の病に倒れました.\n\n医療用ベッドとドクターを確保してください.{PAWN_definite}が 適切な治療を受けられているか確認し,できる限り医療用ベッドで過ごすようにしてください.</NewDisease>
  <!-- EN: {PAWN} has gotten sick from {3}. The infection is in {PAWN_possessive} {1}.\n\nEnsure you have a medical bed and a doctor. Make sure that {PAWN_definite} gets proper treatment and spends as much time in bed as possible. -->
  <NewPartDisease>{PAWN}は {3}の病に倒れました.感染元は {PAWN_possessive} {1}です.医療用ベッドと医者を確保してください.{PAWN_definite}が 適切な治療を受けられているか確認し,できる限り医療用ベッドで過ごすようにしてください.</NewPartDisease>
  <!-- EN: {PAWN_labelShort} has developed an illness: {1} -->
  <NewDiseaseAnimal>{PAWN_labelShort}は 病気を発症しました: {1}</NewDiseaseAnimal>
  <!-- EN: {PAWN_labelShort} has developed an illness: {3} in {PAWN_possessive} {1} -->
  <NewPartDiseaseAnimal>{PAWN_possessive} {1}の{PAWN_labelShort}は 病気を発症しました: {3}</NewPartDiseaseAnimal>

  <!-- EN: {0} was formerly part of your faction. -->
  <PawnWasFormerlyColonist>かつて{0}は 派閥の一員でした.</PawnWasFormerlyColonist>
  <!-- EN: You previously hosted {0}. -->
  <PawnWasFormerlyLodger>{0}は,あなたの世話になったことがあります.</PawnWasFormerlyLodger>
  <!-- EN: {1_labelShort} has these relationships with your colonists: -->
  <PawnHasTheseRelationshipsWithColonists>{1_labelShort}は,入植者達と,これらの関係を持っています:</PawnHasTheseRelationshipsWithColonists>

  <!-- EN: Ancient danger -->
  <LetterLabelAncientShrineWarning>太古の脅威</LetterLabelAncientShrineWarning>
  <!-- EN: As {PAWN_nameDef} draws near the ancient wall, a sense of foreboding overcomes {PAWN_objective}. {PAWN_pronoun} isn't sure why, but {PAWN_pronoun} feels that this dusty structure may contain great danger. -->
  <AncientShrineWarning>予感が,近くにある古代建造物に {0}を 引き寄せました.なぜだか解りませんが,この塵と埃にまみれた廃墟は,大きな危険をはらんでいると {PAWN_pronoun} は感じています.</AncientShrineWarning>

  <!-- EN: We have struck {0}! -->
  <StruckMineable>{0}の鉱脈に突き当たった!</StruckMineable>

  <!-- EN: {0} revenge -->
  <LetterLabelAnimalManhunterRevenge>手負いの{0}</LetterLabelAnimalManhunterRevenge>
  <!-- EN: {1_indefinite} is attacking after being harmed!\n\nIt will hunt any humanoid it can reach. It will calm down when it goes to sleep. -->
  <AnimalManhunterFromDamage>{1_indefinite}は 手負いになって襲いかかったきた!\n\nそいつは手が届く範囲の人間を襲おうとします.眠りにつくと落ち着きを取り戻すでしょう.</AnimalManhunterFromDamage>
  <!-- EN: {1_indefinite} is attacking due to a botched taming attempt! -->
  <AnimalManhunterFromTaming>手なずけるのに失敗し,{1_indefinite}は 襲いかかってきた!</AnimalManhunterFromTaming>
  <!-- EN: Other {1_kindBasePlural} nearby have also become enraged! -->
  <AnimalManhunterOthers>そばにいた,他の{1_kindBasePlural}も いっせいに怒り狂った!</AnimalManhunterOthers>

  <!-- EN: {1_labelShort} hit trap -->
  <LetterFriendlyTrapSprungLabel>{1_labelShort}は 罠にはまった</LetterFriendlyTrapSprungLabel>
  <!-- EN: {1_labelShort} has accidentally sprung a trap and taken damage from it. -->
  <LetterFriendlyTrapSprung>{1_labelShort}は 不慮の事故により,罠で怪我をした.</LetterFriendlyTrapSprung>

  <!-- EN: {PAWN_labelShort} has developed a health condition:\n\n  {1}\n\nThis was caused by:\n\n  {2} -->
  <LetterHealthComplications>{PAWN_labelShort}は, {2}の合併症で, {1}を患った.</LetterHealthComplications>
  <!-- EN: {PAWN_labelShort}: {1} -->
  <LetterHealthComplicationsLabel>{PAWN_labelShort}: {1}</LetterHealthComplicationsLabel>
  
  <!-- EN: {PAWN_labelShort} has developed a health condition: {1}. -->
  <LetterHediffFromRandomHediffGiver>{PAWN_labelShort}は, {1}の病におかされた.</LetterHediffFromRandomHediffGiver>
  <!-- EN: {PAWN_labelShort}: {1} -->
  <LetterHediffFromRandomHediffGiverLabel>{PAWN_labelShort}: {1}</LetterHediffFromRandomHediffGiverLabel>

  <!-- EN: {1} died: {0} -->
  <LetterLeadersDeathLabel>{1}が死亡: {0}</LetterLeadersDeathLabel>
  <!-- EN: {OLDLEADER_nameFull}, {3} of {1}, has died.\n\nThe new {3} is {NEWLEADER_nameFull}. -->
  <LetterLeadersDeath>{1}の{3} {OLDLEADER_nameFull}が死に\n\n新しい{3}は {NEWLEADER_nameFull}になった.</LetterLeadersDeath>

  <!-- EN: New {1}: {0} -->
  <LetterLeaderChangedLabel>新{1}: {0}</LetterLeaderChangedLabel>
  <!-- EN: {OLDLEADER_nameFull} is no longer {3} of {1}.\n\nThe new {3} is {NEWLEADER_nameFull}. -->
  <LetterLeaderChanged>{1}の{3}は,もう{OLDLEADER_nameFull}ではなく\n\n新しい{3}は {NEWLEADER_nameFull}になった.</LetterLeaderChanged>

  <!-- EN: The final straw was: {0} -->
  <FinalStraw>不幸な出来事: {0}</FinalStraw>
  <!-- EN: This happened because of poor mood. -->
  <MentalStateReason_Mood>貧しい心情によって発生した.</MentalStateReason_Mood>
  <!-- EN: This happened because of the trait: {0}. -->
  <MentalStateReason_Trait>特性・特徴によって発止した: {0}.</MentalStateReason_Trait>
  <!-- EN: This happened because of: {0}. -->
  <MentalStateReason_Hediff>{0}によって発生した.</MentalStateReason_Hediff>
  <!-- EN: This happened because of {0_definite}'s death. -->
  <MentalStateReason_BondedHumanDeath>{0_definite}の死が引き金になり発生した.</MentalStateReason_BondedHumanDeath>
  <!-- EN: The last event was -->
  <LastFactionRelationsEvent>きっかけとなった出来事</LastFactionRelationsEvent>

  <!-- EN: View related quest -->
  <ViewRelatedQuest>関連するクエストを参照</ViewRelatedQuest>
  <!-- EN: View quest -->
  <ViewQuest>クエストを参照</ViewQuest>
  <!-- EN: The last events in {PAWN_definite}'s life -->
  <LastEventsInLife>{PAWN_definite}の人生で 最後に起きた出来事</LastEventsInLife>

  <!-- Related pawns -->
  <!-- EN: Relationship -->
  <LetterLabelNoticedRelatedPawns>血縁関係</LetterLabelNoticedRelatedPawns>
  <!-- EN: There are people who have relationships with your {0} or prisoners in the arriving group of {1}.\n\nKeep in mind that even though they are related, they will still attack each other because of their bad factions relations.\n\nThese people are: -->
  <LetterRelatedPawnsRaidEnemy>あなたのコロニーの{0}か,囚人と,繋がりの有る者が,到着した敵対する {1} グループにいます.\n\nたとえ血が繋がっていても,敵対関係にある以上,依然として襲ってくることには,変わりが無いことに留意してください.\n\n 家族の一員：</LetterRelatedPawnsRaidEnemy>
  <!-- EN: There are people who have relationships with your {0} or prisoners in the arriving group of friendly {1}: -->
  <LetterRelatedPawnsRaidFriendly>あなたのコロニーの{0}か,囚人と,繋がりの有る者が,到着した友好な {1} グループにいます:</LetterRelatedPawnsRaidFriendly>
  <!-- EN: There are people who have relationships with your {0} or prisoners in the arriving group: -->
  <LetterRelatedPawnsNeutralGroup>あなたのコロニーの{0}か,囚人と,繋がりの有る者が,到着したグループにいます：</LetterRelatedPawnsNeutralGroup>
  <!-- EN: The orbital trader is selling people who have relationships with your {0} or prisoners: -->
  <LetterRelatedPawnsTradeShip>あなたのコロニーの{0}か,囚人と,繋がりの有る者が,軌道トレーダーによって売られています:</LetterRelatedPawnsTradeShip>
  <!-- EN: The settlement is selling people who have relationships with your {0} or prisoners: -->
  <LetterRelatedPawnsTradingWithSettlement>あなたのコロニーの{0}か,囚人と,繋がりの有る者が,拠点で売られています:</LetterRelatedPawnsTradingWithSettlement>
  <!-- EN: The caravan is selling people who have relationships with your {0} or prisoners: -->
  <LetterRelatedPawnsTradingWithOtherCaravan>あなたのコロニーの{0}か,囚人と,繋がりの有る者が,他キャラバン隊によって売られています:</LetterRelatedPawnsTradingWithOtherCaravan>
  <!-- EN: There are people who have relationships with your {0} or prisoners in the group: -->
  <LetterRelatedPawnsGroupGeneric>あなたのコロニーの{0}か,囚人と,繋がりの有る者がグループにいます:</LetterRelatedPawnsGroupGeneric>
  <!-- EN: There are people who have relationships with your {0} or prisoners in the area where your {0} have landed. -->
  <LetterRelatedPawnsInMapWherePlayerLanded>あなたのコロニーの{0}か,囚人と,繋がりの有る者が,このエリアにいます.</LetterRelatedPawnsInMapWherePlayerLanded>
  <!-- EN: There are people who have relationships with your {0} or prisoners in this settlement: -->
  <LetterRelatedPawnsSettlement>あなたのコロニーの{0}か,囚人と,繋がりの有る者が,ここの拠点にいます:</LetterRelatedPawnsSettlement>
  <!-- EN: There are people who have relationships with your {0} or prisoners in this area: -->
  <LetterRelatedPawnsSite>あなたのコロニーの{0}か,囚人と,繋がりの有る者が,このエリアにいます:</LetterRelatedPawnsSite>

  <!-- EN: relationship -->
  <RelationshipAppendedLetterSuffix>(血縁関係)</RelationshipAppendedLetterSuffix>
  <!-- EN: {PAWN_nameDef} has a relationship with a colonist. {PAWN_pronoun} is {RELATIVE_labelShort}'s {1}. -->
  <RelationshipAppendedLetterTextColonist>{PAWN_nameDef} は入植者と血縁関係にあります.{PAWN_pronoun}は {RELATIVE_labelShort}の {1}です.</RelationshipAppendedLetterTextColonist>
  <!-- EN: {PAWN_nameDef} has a relationship with one of your prisoners. {PAWN_pronoun} is {RELATIVE_labelShort}'s {1}. -->
  <RelationshipAppendedLetterTextPrisoner>{PAWN_nameDef} は囚人の一人と血縁関係にあります.{PAWN_pronoun}は {RELATIVE_labelShort}の {1}です.</RelationshipAppendedLetterTextPrisoner>

  <!-- Attempt romance / propose interaction -->
  <!-- EN: Affair -->
  <LetterLabelAffair>浮気</LetterLabelAffair>
  <!-- EN: {PAWN1_labelShort}, married to {SPOUSE_labelShort}, has begun an affair with {PAWN2_labelShort}. -->
  <LetterAffair>{PAWN1_labelShort}は {SPOUSE_labelShort}と結婚しているのも関わらず, {PAWN2_labelShort}に うつつを抜かしています.</LetterAffair>
  <!-- EN: New lovers -->
  <LetterLabelNewLovers>新しい恋人達</LetterLabelNewLovers>
  <!-- EN: {PAWN1_labelShort} and {PAWN2_labelShort} now want to sleep together. Consider assigning them a double bed. -->
  <LetterNewLovers>{PAWN1_labelShort}と {PAWN2_labelShort}は 互いに寄り添って眠りたがっています.彼らにダブルベッドはどうでしょう.</LetterNewLovers>
  <!-- EN: {PAWN1_labelShort} and {PAWN2_labelShort} are no longer in a relationship. -->
  <LetterNoLongerLovers>{PAWN1_labelShort}と {PAWN2_labelShort}は その関係を断ちました.</LetterNoLongerLovers>
  <!-- EN: {PAWN_labelShort} will change {PAWN_possessive} last name back to {PAWN_possessive} birth name. -->
  <LetterNoLongerLovers_BackToBirthName>{PAWN_labelShort}の名字は旧姓に戻ります.</LetterNoLongerLovers_BackToBirthName>
  <!-- EN: Breakup -->
  <LetterLabelBreakup>振られた</LetterLabelBreakup>
  <!-- EN: Marriage is on! -->
  <LetterLabelAcceptedProposal>喜んで!結婚しよう</LetterLabelAcceptedProposal>
  <!-- EN: Rejected proposal -->
  <LetterLabelRejectedProposal>ごめんなさい</LetterLabelRejectedProposal>
  <!-- EN: At some point in the coming days or quadrums, they will have their marriage ceremony and invite all the colonists. Consider placing a marriage spot if you want to control where the ceremony occurs. -->
  <LetterAcceptedProposal>来るべき日がくれば,彼らは結婚式を執り行い,すべての入植者を招待します.どこで結婚式を行うかを思い通りにしたければ,結婚を誓う場の検討をします.</LetterAcceptedProposal>
  <!-- EN: {PAWN_label} will change {PAWN_possessive} last name to {1}. -->
  <LetterAcceptedProposal_NameChange>{PAWN_label}の名字は {1}に変わります.</LetterAcceptedProposal_NameChange>
  <!-- EN: {INITIATOR_nameFull} is going to be unhappy about this. -->
  <LetterRejectedProposal>{INITIATOR_nameFull}は,このことで不幸になるでしょう.</LetterRejectedProposal>

  <!-- Generalized letter labels -->
  <!-- EN: Hostile: {0} -->
  <LetterLabelRelationsChange_Hostile>敵対: {0}</LetterLabelRelationsChange_Hostile>
  <!-- EN: Allied: {0} -->
  <LetterLabelRelationsChange_Ally>同盟: {0}</LetterLabelRelationsChange_Ally>
  <!-- EN: Enemy now neutral: {0} -->
  <LetterLabelRelationsChange_NeutralFromHostile>敵対から中立へ: {0}</LetterLabelRelationsChange_NeutralFromHostile>
  <!-- EN: Ally now neutral: {0} -->
  <LetterLabelRelationsChange_NeutralFromAlly>同盟から中立へ: {0}</LetterLabelRelationsChange_NeutralFromAlly>
  <!-- EN: Zzztt... -->
  <LetterLabelShortCircuit>バチバチ...</LetterLabelShortCircuit>

  <!-- Bonded animals -->
  <!-- EN: bonded -->
  <LetterLabelSuffixBondedAnimalDied>絆で結ばれた</LetterLabelSuffixBondedAnimalDied>
  <!-- EN: {ANIMAL_definite} was bonded to {HUMAN_labelShort}. It will affect {HUMAN_labelShort}'s mood. -->
  <LetterPartBondedAnimalDied>{ANIMAL_definite}は{HUMAN_labelShort}と絆で結ばれました.{HUMAN_labelShort}の"心情"に影響を及ぼすでしょう.</LetterPartBondedAnimalDied>
  <!-- EN: It will affect mood of the following people:\n\n{0} -->
  <LetterPartBondedAnimalDiedMulti>次の人々の"心情"に影響を及ぼします:\n\n{0}</LetterPartBondedAnimalDiedMulti>

  <!-- Prison break -->
  <!-- EN: Prison break -->
  <LetterLabelPrisonBreak>脱走</LetterLabelPrisonBreak>
  <!-- EN: Prisoners have staged a breakout! They've somehow defeated the door locks and are making their way out. They may seek weapons, fight, or try to escape. These prisoners are involved:\n\n{0}\n\nPrisoners are more likely to attempt breakout when they are numerous and healthy. -->
  <LetterPrisonBreak>囚人たちが脱走しました!.どうやったかは知らないが,彼らは,ドアのロックを壊して逃げ出しました.彼らは武器を探し,戦ってでも逃げようとします.\n\n指名手配：\n\n{0}\n\n囚人たちを,多数ひとまとめにして,不満を放っておいたり,不健康のままにしておくと,より脱走を試みるようになります.</LetterPrisonBreak>

  <!-- Newly addicted -->
  <!-- EN: {0} addiction -->
  <LetterLabelNewlyAddicted>{0}依存症</LetterLabelNewlyAddicted>
  <!-- EN: {PAWN_labelShort} has developed an addiction to {1}.\n\n{PAWN_pronoun} now has a need for {1}, visible on {PAWN_possessive} Needs tab. {PAWN_pronoun} will automatically consume the drug to fulfil {PAWN_possessive} need. If {PAWN_pronoun} cannot get any {1}, {PAWN_pronoun} will go into withdrawal. -->
  <LetterNewlyAddicted>{PAWN_labelShort}は,{1}依存症を患いました.\n\n今や{PAWN_pronoun}には{1}に対する欲求があり,それは{PAWN_possessive}「欲求」タブで見て取れます. {PAWN_pronoun}は自身の欲求を満たすために,勝手にドラッグを消費するようになります. もし{PAWN_pronoun}が{1}を手に入れられなければ,{PAWN_pronoun}は離脱症状を起こすことになるでしょう.</LetterNewlyAddicted>

  <!-- Drug binge -->
  <!-- EN: {0} binge -->
  <LetterLabelDrugBinge>{0} 浪費</LetterLabelDrugBinge>
  <!-- EN: {2_label} is binging on {1}. -->
  <LetterDrugBinge>{2_label}は, {1}を 浪費するようになった.</LetterDrugBinge>

  <!-- Caravan destroyed -->
  <!-- EN: Caravan destroyed -->
  <LetterLabelAllCaravanColonistsDied>キャラバン隊壊滅</LetterLabelAllCaravanColonistsDied>
  <!-- EN: All members of {0} have died. -->
  <LetterAllCaravanColonistsDied>{0}の全員が死亡しました.</LetterAllCaravanColonistsDied>

  <!-- Caravan entered map -->
  <!-- EN: Caravan arrived at {0_label} -->
  <LetterLabelCaravanEnteredMap>{0_label}に到着</LetterLabelCaravanEnteredMap>
  <!-- EN: {0} has arrived at {1_definite}. -->
  <LetterCaravanEnteredMap>{0}は,{1_definite}に到着しました.</LetterCaravanEnteredMap>

  <!-- Caravan entered enemy base -->
  <!-- EN: Attack begun -->
  <LetterLabelCaravanEnteredEnemyBase>戦闘開始</LetterLabelCaravanEnteredEnemyBase>
  <!-- EN: {0} has arrived at {1} and is ready to begin the attack. -->
  <LetterCaravanEnteredEnemyBase>{0}は,{1}に到着し,攻撃準備は整っています.</LetterCaravanEnteredEnemyBase>

  <!-- Transport pods landed in enemy base -->
  <!-- EN: Attack begun -->
  <LetterLabelTransportPodsLandedInEnemyBase>戦闘開始</LetterLabelTransportPodsLandedInEnemyBase>
  <!-- EN: Your transport pods have arrived at {0}. -->
  <LetterTransportPodsLandedInEnemyBase>あなたの輸送ポッドが{0}に着きました.</LetterTransportPodsLandedInEnemyBase>

  <!-- Faction base defeated -->
  <!-- EN: Base destroyed -->
  <LetterLabelFactionBaseDefeated>拠点破壊</LetterLabelFactionBaseDefeated>
  <!-- EN: The enemy base {0} has been destroyed.\n\nIn {1}, the caravan will automatically be reformed. You can reform the caravan now in the World screen by selecting the destroyed base and choosing the "Reform caravan" option. -->
  <LetterFactionBaseDefeated>敵の拠点"{0}"を破壊しました.\n\n{1}で,キャラバン隊は自動的に再編成されます.あなたはワールドマップから,敵拠点の破壊と,"キャラバン隊の再編成"を選ぶこともできます.</LetterFactionBaseDefeated>
  <!-- EN: This was the last base of {0}, which means this faction doesn't exist anymore. -->
  <LetterFactionBaseDefeated_FactionDestroyed>ここが{0}の最後の砦でした,つまりは,この派閥はもう何処にも居ません.</LetterFactionBaseDefeated_FactionDestroyed>

  <!-- Quest completed -->
  <!-- EN: Quest completed -->
  <LetterLabelDefeatAllEnemiesQuestCompleted>クエスト完了</LetterLabelDefeatAllEnemiesQuestCompleted>
  <!-- EN: You have defeated the enemy outpost!\n\nThe payment from {0} has arrived, and faction relations have improved by {1}. -->
  <LetterDefeatAllEnemiesQuestCompleted>貴方は前哨基地の敵を倒しました!\n\n{0}からの,報奨金が到着し,{1}による,派閥関係が良くなりました.</LetterDefeatAllEnemiesQuestCompleted>

  <!-- Long-range mineral scanner -->
  <!-- EN: Distant resource scanned -->
  <LetterLabelFoundPreciousLump>稀少鉱物を探知</LetterLabelFoundPreciousLump>
  <!-- EN: Using your long-range mineral scanner, {WORKER_labelShort} has found a lump of {0} some distance away.\n\nUnfortunately, it won't last - others will mine it first in {1} days if we don't.\n\n{2}. -->
  <LetterFoundPreciousLump>長距離鉱物スキャナーを使用して,{WORKER_labelShort}は,すぐ近くに{0}鉱床を発見した.\n\n残念ながら,そう長くは持たない - 他の住人が{1}日以内に先に採掘するだろう・・\n\n{2}</LetterFoundPreciousLump>

  <!-- Ground penetrating scanner -->
  <!-- EN: Scanned underground -->
  <LetterLabelDeepScannerFoundLump>地質を走査した</LetterLabelDeepScannerFoundLump>
  <!-- EN: {FINDER_nameDef} has found a lump of buried {0} using the ground-penetrating scanner! -->
  <LetterDeepScannerFoundLump>地質貫通型スキャナーを使用して,{FINDER_nameDef}は{0}鉱床を発見した!.</LetterDeepScannerFoundLump>

  <!-- Ambush -->
  <!-- EN: Ambush -->
  <LetterLabelAmbushInExistingMap>待ち伏せ</LetterLabelAmbushInExistingMap>
  <!-- EN: Your {0} have been ambushed! -->
  <LetterAmbushInExistingMap>{0}は待ち伏せされた!</LetterAmbushInExistingMap>

  <!-- Peace talks -->
  <!-- EN: Peace talks disaster -->
  <LetterLabelPeaceTalks_Disaster>和平交渉 決裂</LetterLabelPeaceTalks_Disaster>
  <!-- EN: The talks were a disaster. The delegates barely got past their initial greetings before the discussion broke down into insults and recriminations.\n\nAfter your caravan departed early, {0} from {1} caught up with it and attacked!\n\nRelations with {1}: {2}. -->
  <LetterPeaceTalks_Disaster>交渉は決裂した.代表団は,協議が,侮辱と非難のなすり合いで決裂する前に,かろうじて冒頭の挨拶をやり過ごしたに過ぎなかった.\n\n早々と貴方のキャラバン隊が出発した後,{1}からの {0}は追って来て,攻撃してきた!\n\n {1}との関係: {2}</LetterPeaceTalks_Disaster>
  <!-- EN: Peace talks backfire -->
  <LetterLabelPeaceTalks_Backfire>和平交渉 逆効果</LetterLabelPeaceTalks_Backfire>
  <!-- EN: The talks have backfired. Despite trading some pleasantries, the delegates made no progress on substantive issues, and multiple statements were interpreted as insults.\n\nRelations with {0}: {1}. -->
  <LetterPeaceTalks_Backfire>交渉は裏目に出た.いくつかの嘲笑と引き換えたにも関わらず,代表団は,実質的な問題に対して進展が無く,複数の声明は侮辱とみなされた.\n\n {0}との関係: {1}</LetterPeaceTalks_Backfire>
  <!-- EN: Peace talks flounder -->
  <LetterLabelPeaceTalks_TalksFlounder>和平交渉 難航</LetterLabelPeaceTalks_TalksFlounder>
  <!-- EN: The talks floundered. Delegates managed to communicate clearly and with basic respect, but were not able to make progress on any genuine issues.\n\nRelations with {0} remain unchanged. -->
  <LetterPeaceTalks_TalksFlounder>交渉は難航している.代表団は,基本的な敬意を払って,かろうじて明確に伝えることができたが,主となる問題について親展を得ることは出来なかった.\n\n {0}との関係: 変化無し</LetterPeaceTalks_TalksFlounder>
  <!-- EN: Peace talks success -->
  <LetterLabelPeaceTalks_Success>和平交渉 成功</LetterLabelPeaceTalks_Success>
  <!-- EN: The talks were a success. The delegates reached new mutual understanding on several substantial issues.\n\nRelations with {0} have improved by {1}. -->
  <LetterPeaceTalks_Success>交渉は成功した.代表団は,幾つかの実質的な問題に対して,新しい相互理解に達した.\n\n {0}との関係は {1}によって改善した.</LetterPeaceTalks_Success>
  <!-- EN: Peace talks triumph -->
  <LetterLabelPeaceTalks_Triumph>和平交渉 大勝利</LetterLabelPeaceTalks_Triumph>
  <!-- EN: The talks were a great triumph! Delegates connected quickly on a personal level and came to truly see each others' perspective on the most difficult issues of the day.\n\nRelations with {0} have improved by {1}.\n\nAs your caravan departed, {0} offered you a gift:\n\n{2} -->
  <LetterPeaceTalks_Triumph>交渉は大勝利に終わった! 代表団は,迅速に個人レベルでお互いに理解し合い,最も難しい問題に対する,お互いの展望のため,心から集まった.\n\n {0}との関係は {1}によって改善した.\n\n 貴方のキャラバン隊が出発のとき,{0}は贈り物を申し出た: {2}</LetterPeaceTalks_Triumph>
  <!-- EN: {PAWN_labelShort}, your negotiator, has gained {1} social experience. -->
  <PeaceTalksSocialXPGain>交渉人 {PAWN_labelShort}は {1}経験値をためた.</PeaceTalksSocialXPGain>

  <!-- Run wild mental break -->
  <!-- EN: {0} is fed up with civilization.\n\n{PAWN_pronoun} realized that wild creatures are always free. So, {PAWN_pronoun} has decided to leave your faction and live with the animals.\n\nYou can attempt to tame or arrest {PAWN_objective} to get {PAWN_objective} back. -->
  <LetterRunWildMentalBreak>{0}は文明にうんざりしています.\n\n{PAWN_pronoun}は,野生動物達は常に自由だということに気がつきました.{PAWN_pronoun}は,あなたの派閥を離れて,動物達と共に生きていくことに決めました.\n\nあなたは,{PAWN_objective}手懐けて連れ戻す試みができます.</LetterRunWildMentalBreak>

  <!-- Catatonic mental break -->
  <!-- EN: {0} has suffered a total mental breakdown and entered a catatonic state. {PAWN_pronoun} will recover in several days. -->
  <LetterCatatonicMentalBreak>{0}は完全に精神崩壊を起こし,カタトニーとなりました.{PAWN_pronoun}は数日で正常な状態に回復するでしょう.</LetterCatatonicMentalBreak>

  <!-- EN: Persona Core Offer -->
  <LetterLabelAICoreOffer>AIコア 提示</LetterLabelAICoreOffer>
  <!-- EN: {PAWN_definite} of {1} contacts you with an offer of information: the location of a persona core, which you'll need in order to build a spaceship. They inform you that this item is quite rare and usually its owners have it under heavy guard.\n\nCall them with your comms console if you're interested. -->
  <LetterAICoreOffer>{1}の{PAWN_definite}が,次の提供情報を携えて,あなたに接触してきました:あなたが宇宙船を建造するのに必要なAI人格コアの座標.このアイテムは本当に貴重であり,このアイテム所持者は大抵,厳重な保護の元に置いてることを,彼らは伝えてきた.\n\nもし興味があるなら,通信機で彼らを呼び出してください.</LetterAICoreOffer>

  <!-- Crafting letters -->
  <!-- EN: Legendary Work -->
  <LetterCraftedLegendaryLabel>伝説的な仕事</LetterCraftedLegendaryLabel>
  <!-- EN: {WORKER_labelShort} has created a {CRAFTED_labelShort}.\n\nNews of this valuable artifact will spread across the world. -->
  <LetterCraftedLegendaryMessage>{WORKER_labelShort}は,{CRAFTED_labelShort}を作り上げました.\n\nこの高価なアーティファクトに関するニュースは世界中へと拡散されました.</LetterCraftedLegendaryMessage>
  <!-- EN: {WORKER_labelShort} has created a {CRAFTED_labelShort}.\n\n{0}\n\nNews of this valuable artifact will spread across the world. -->
  <LetterCraftedLegendaryMessageArt>{WORKER_labelShort}は,{CRAFTED_labelShort}を創り上げました.\n\n{0}\n\nこの高価な芸術品に関するニュースは世界中へと拡散されました.</LetterCraftedLegendaryMessageArt>

  <!-- EN: Masterwork -->
  <LetterCraftedMasterworkLabel>傑作</LetterCraftedMasterworkLabel>
  <!-- EN: {WORKER_labelShort} has created a {CRAFTED_labelShort}. -->
  <LetterCraftedMasterworkMessage>{WORKER_labelShort}は,{CRAFTED_labelShort}を作り上げました.</LetterCraftedMasterworkMessage>
  <!-- EN: {WORKER_labelShort} has created a {CRAFTED_labelShort}.\n\n{0} -->
  <LetterCraftedMasterworkMessageArt>{WORKER_labelShort}は,{CRAFTED_labelShort}を創り上げました.\n\n{0}</LetterCraftedMasterworkMessageArt>

  <!-- Pawns lost because map closed -->
  <!-- EN: Caravan lost -->
  <LetterLabelPawnsLostBecauseMapClosed_Caravan>キャラバン隊全滅</LetterLabelPawnsLostBecauseMapClosed_Caravan>
  <!-- EN: Your caravan has been lost. The following people and animals have been lost with it -->
  <LetterPawnsLostBecauseMapClosed_Caravan>キャラバン隊は全滅し,次の人々もろとも家畜も一緒に失いました.</LetterPawnsLostBecauseMapClosed_Caravan>
  <!-- EN: Inhabitants abandoned -->
  <LetterLabelPawnsLostBecauseMapClosed_Home>住民の放棄</LetterLabelPawnsLostBecauseMapClosed_Home>
  <!-- EN: The following people and animals have been abandoned -->
  <LetterPawnsLostBecauseMapClosed_Home>次の人々と家畜は放棄されました.</LetterPawnsLostBecauseMapClosed_Home>

  <!-- Hibernate complete -->
  <!-- EN: Reactor ready -->
  <LetterLabelHibernateComplete>反応炉 準備完了</LetterLabelHibernateComplete>
  <!-- EN: <Name>Charlon Whitestone</Name> has finished the reactor's hibernation recovery sequence. The reactor is now ready to power a liftoff. -->
  <LetterHibernateComplete>Charlon Whitestoneは,反応炉の再起動シーケンスを完了させました.いま,反応炉は打ち上げに必要なパワーの準備が出来ています.</LetterHibernateComplete>
  <!-- EN: The reactor's power up sequence is complete. It is now ready to power a liftoff. -->
  <LetterHibernateCompleteStandalone>反応炉の再起動シーケンスは完了しました.打ち上げ準備は完了です.</LetterHibernateCompleteStandalone>

  <!-- Visitors gave gift -->
  <!-- EN: Gift from {0} -->
  <LetterLabelVisitorsGaveGift>{0}からの貢ぎ物</LetterLabelVisitorsGaveGift>
  <!-- EN: {0} from {PAWN_factionName} have left a gift:\n\n{1} -->
  <LetterVisitorsGaveGift>{PAWN_factionName}の{0}から貢ぎ物が届きました:\n\n{1}</LetterVisitorsGaveGift>

  <!-- Faction base proximity -->
  <!-- EN: Faction base proximity -->
  <LetterLabelFactionBaseProximity>近接した派閥拠点</LetterLabelFactionBaseProximity>
  <!-- EN: Because you are so close to other factions, they feel you're encroaching on their territory.\n\nFor the last quadrum, faction relations have been reduced by: -->
  <LetterFactionBaseProximity>あなたは他の派閥にとても近づきすぎたので,彼らは,彼らの領土に,あなたが割り込んできたと感じています.\n\n派閥関係が悪くなります:</LetterFactionBaseProximity>

  <!-- Caravans battlefield victory -->
  <!-- EN: Caravan battle won -->
  <LetterLabelCaravansBattlefieldVictory>キャラバン隊勝利</LetterLabelCaravansBattlefieldVictory>
  <!-- EN: Your caravan has won the battle.\n\nYou can reform the caravan now in the World screen by selecting the battlefield and choosing the "Reform caravan" option.\n\nThere's no need to collect items manually, the reform caravan tool can do it instantly.\n\nIn {0}, the caravan will be reformed automatically. -->
  <LetterCaravansBattlefieldVictory>あなたのキャラバン隊は戦闘に勝利しました.\n\nあなたはワールドマップから,拠点の選択と,"キャラバン隊の再編成"を選ぶことができます.\n\nアイテム収集を手動で行う必要はありません,キャラバン隊再編成コマンドで簡単にできます.\n\n{0}で,キャラバン隊は自動的に再編成されます.</LetterCaravansBattlefieldVictory>

  <!-- Rescue quest -->
  <!-- EN: Rescuee joins -->
  <LetterLabelRescueQuestFinished>レスキュー＆参加</LetterLabelRescueQuestFinished>
  <!-- EN: You have rescued {PAWN_nameDef} and {PAWN_pronoun} has joined your group.\n\nYou can take {PAWN_objective} with you by reforming the caravan in the World screen by selecting this area and choosing the "Reform caravan" option. -->
  <LetterRescueQuestFinished>{PAWN_nameDef}を助けて,{PAWN_pronoun}はグループに加わりました.\n\nあなたはワールドマップから,"キャラバン隊の再編成"を選ぶことで,キャラバン隊の再編成を行い,{PAWN_objective}連れて行く事ができます.</LetterRescueQuestFinished>

  <!-- Predator hunting colonist -->
  <!-- EN: {PREDATOR_labelShort} hunting {PREY_definite} -->
  <LetterLabelPredatorHuntingColonist>{PREDATOR_labelShort}は{PREY_definite}を狩っている</LetterLabelPredatorHuntingColonist>
  <!-- EN: {PREDATOR} is hunting {PREY_definite} for food! -->
  <LetterPredatorHuntingColonist>{PREDATOR}はエサとして{PREY_definite}を狩っている!</LetterPredatorHuntingColonist>

  <!-- Disease -->
  <!-- EN: {0} blocked {1} on: {2}. -->
  <LetterDisease_Blocked>{0}はブロックされている {1} : {2}.</LetterDisease_Blocked>
  <!-- EN: Disease: {0} -->
  <LetterLabelTraitDisease>疫病 ({0})</LetterLabelTraitDisease>
  <!-- EN: {PAWN_label} has gotten sick from {1}.\n\nEnsure you have a medical bed and a doctor. Make sure that {PAWN_pronoun} gets proper treatment and spends as much time in bed as possible. -->
  <LetterTraitDisease>{PAWN_label}は {1}の病に倒れました.\n\n医療用ベッドとドクターを確保してください. {PAWN_pronoun}が 適切な治療を受けられているか確認し,できる限り医療用ベッドで過ごすようにしてください.</LetterTraitDisease>

  <!-- Quests -->
  <!-- EN: A new quest has become available. It is called '{0}'. -->
  <LetterQuestBecameAvailable>新しいクエスト {0} が入手可能になりました.</LetterQuestBecameAvailable>
  <!-- EN: If you don’t accept the quest within {0}, it will expire. -->
  <LetterQuestRequiresAcceptance>このクエストは,{0}以内に受領しないと期限切れになります.</LetterQuestRequiresAcceptance>
  <!-- EN: A new quest has become active. It is called '{0}'. -->
  <LetterQuestBecameActive>新しいクエスト {0} を受領しました.</LetterQuestBecameActive>
  <!-- EN: Quest active: {0} -->
  <LetterQuestAutomaticallyAcceptedTitle>クエスト受領: {0}</LetterQuestAutomaticallyAcceptedTitle>
  <!-- EN: It will expire in {0}. -->
  <LetterQuestActiveNowTime>有効期限 {0}.</LetterQuestActiveNowTime>

  <!-- Quest drop pods arrived -->
  <!-- EN: Pods arrived -->
  <LetterLabelQuestDropPodsArrived>ポッド到着</LetterLabelQuestDropPodsArrived>
  <!-- EN: Transport pods with the following contents have arrived:\n\n{0} -->
  <LetterQuestDropPodsArrived>次の積荷を積んだ輸送ポッドが到着しました:\n\n{0}</LetterQuestDropPodsArrived>

  <!-- Refugee joins -->
  <!-- EN: {PAWN_nameDef} joins -->
  <LetterLabelRefugeeJoins>{PAWN_nameDef}が仲間に</LetterLabelRefugeeJoins>
  <!-- EN: A {PAWN_title} named {PAWN_nameDef} has arrived and is joining the colony. -->
  <LetterRefugeeJoins>{PAWN_nameDef}と名乗る{PAWN_title}が到着しコロニーに加わりました.</LetterRefugeeJoins>
  
  <!-- Rescuee joins -->
  <!-- EN: {PAWN_nameDef} joins -->
  <LetterLabelRescueeJoins>{PAWN_nameDef}が参加</LetterLabelRescueeJoins>
  <!-- EN: {PAWN_nameDef} is thankful that you rescued {PAWN_objective}. {PAWN_pronoun} has decided that {PAWN_pronoun} would rather stay than leave, and is joining your colony. -->
  <LetterRescueeJoins>{PAWN_nameDef}は あなたが助けた{PAWN_objective}に感謝しています. {PAWN_pronoun}は,ここを離れるより,みんなと一緒に居たほうが良いと判断しコロニーに参加します.</LetterRescueeJoins>

  <!-- Pawns arrive and join -->
  <!-- EN: People join -->
  <LetterLabelPawnsArriveAndJoin>参入者</LetterLabelPawnsArriveAndJoin>
  <!-- EN: The following people have arrived and joined the colony:\n\n{0} -->
  <LetterPawnsArriveAndJoin>これらの人達が到着しコロニーに加わります:\n\n{0}</LetterPawnsArriveAndJoin>

  <!-- Pawns arrive -->
  <!-- EN: People arrived -->
  <LetterLabelPawnsArrive>到着</LetterLabelPawnsArrive>
  <!-- EN: The following people have arrived:\n\n{0} -->
  <LetterPawnsArrive>これらの人達が到着しました:\n\n{0}</LetterPawnsArrive>

  <!-- Pawn leaving -->
  <!-- EN: {0} leaving -->
  <LetterLabelPawnLeaving>{0}は去っていきます</LetterLabelPawnLeaving>
  <!-- EN: {0} is leaving. -->
  <LetterPawnLeaving>{0}は去っていきます</LetterPawnLeaving>

  <!-- Pawns leaving -->
  <!-- EN: {0} leaving -->
  <LetterLabelPawnsLeaving>{0}は去っていきます</LetterLabelPawnsLeaving>
  <!-- EN: {0} are leaving. -->
  <LetterPawnsLeaving>{0}は去っていきます</LetterPawnsLeaving>
  
  <!-- Colonist kidnapped -->
  <!-- EN: {PAWN_nameDef} kidnapped -->
  <LetterLabelPawnsKidnapped>{PAWN_nameDef}が誘拐された</LetterLabelPawnsKidnapped>
  <!-- EN: {PAWN_nameDef} has been kidnapped by {FACTION_name}!
\nHowever, {PAWN_pronoun} is not lost forever. An opportunity to rescue {PAWN_objective} may present itself in the coming days or years. -->
  <LetterPawnsKidnapped>{FACTION_name}によって{PAWN_nameDef}は連れ去られました!\nでも{PAWN_pronoun}を諦めることはありません. {PAWN_objective}を救出する機会は,きっと訪れるはずです.</LetterPawnsKidnapped>
  
  <!-- Techprints -->
  <!-- EN: Techprint applied: {PROJECT_label} -->
  <LetterTechprintAppliedLabel>Techprint applied: {PROJECT_label}</LetterTechprintAppliedLabel>
  <!-- EN: A techprint has been applied to the research project: {PROJECT_label}. -->
  <LetterTechprintAppliedPartIntro>A techprint has been applied to the research project: {PROJECT_label}.</LetterTechprintAppliedPartIntro>
  <!-- EN: You've completed the project's techprint requirements! Your researchers can now begin researching how to actually use the technology at your research benches. -->
  <LetterTechprintAppliedPartJustUnlocked>You've completed the project's techprint requirements! Your researchers can now begin researching how to actually use the technology at your research benches.</LetterTechprintAppliedPartJustUnlocked>
  <!-- EN: This project's techprint requirements are not yet satisfied. {0} techprints have been applied so far. The project requires {1} in total. -->
  <LetterTechprintAppliedPartNotUnlockedYet>This project's techprint requirements are not yet satisfied. {0} techprints have been applied so far. The project requires {1} in total.</LetterTechprintAppliedPartNotUnlockedYet>
  <!-- EN: This project's techprint requirements were already satisfied. The extra techprint advanced your research efforts on {PROJECT_label}. Half the remaining research work, {0} points, has been completed. -->
  <LetterTechprintAppliedPartAlreadyUnlocked>This project's techprint requirements were already satisfied. The extra techprint advanced your research efforts on {PROJECT_label}. Half the remaining research work, {0} points, has been completed.</LetterTechprintAppliedPartAlreadyUnlocked>
  <!-- EN: This project is already fully researched, so the techprint didn't advance your knowledge at all. -->
  <LetterTechprintAppliedPartAlreadyResearched>This project is already fully researched, so the techprint didn't advance your knowledge at all.</LetterTechprintAppliedPartAlreadyResearched>
  <!-- EN: By applying the techprint, {PAWN_labelShort} gained {0} experience in the {1} skill. -->
  <LetterTechprintAppliedPartExpAwarded>By applying the techprint, {PAWN_labelShort} gained {0} experience in the {1} skill.</LetterTechprintAppliedPartExpAwarded>
  
  <!-- Quest Completed -->
  <!-- EN: Quest completed -->
  <LetterQuestCompletedLabel>クエスト完了</LetterQuestCompletedLabel>
  <!-- EN: Quest failed -->
  <LetterQuestFailedLabel>クエスト失敗</LetterQuestFailedLabel>
  <!-- EN: Quest concluded -->
  <LetterQuestConcludedLabel>クエスト完結</LetterQuestConcludedLabel>
  <!-- EN: You have successfully completed the quest '{0}'! -->
  <LetterQuestCompletedSuccess>'{0}'クエストを成功させた!</LetterQuestCompletedSuccess>
  <!-- EN: You have failed the quest '{0}'. -->
  <LetterQuestCompletedFail>'{0}'クエストを失敗させた.</LetterQuestCompletedFail>
  <!-- EN: You have concluded the quest '{0}'. -->
  <LetterQuestCompletedConcluded>あなたはクエスト'{0}'を完結させました.</LetterQuestCompletedConcluded>
  
  <!-- Bladelink -->
  <!-- EN: Bladelink bond: {PAWN_labelShort} -->
  <LetterBladelinkWeaponBondedLabel>護り刀: {PAWN_labelShort}</LetterBladelinkWeaponBondedLabel>
  <!-- EN: {PAWN_labelShort} has established a bond with the persona of {WEAPON_labelShort}.
\nFrom now on, {WEAPON_labelShort} will refuse to be wielded by anyone except {PAWN_labelShort}. -->
  <LetterBladelinkWeaponBonded>{PAWN_labelShort}は {WEAPON_labelShort}の人格と親密な絆を確立した.\nこの瞬間より,{WEAPON_labelShort}は,{PAWN_labelShort}以外に,扱われるのを拒絶するだろう.</LetterBladelinkWeaponBonded>
  
  <!-- Mech cluster -->
  <!-- EN: Mechanoids arrived -->
  <LetterLabelMechClusterArrived>メカノイド到着</LetterLabelMechClusterArrived>
  <!-- EN: Mechanoids have arrived. -->
  <LetterMechClusterArrived>メカノイドが到着した.</LetterMechClusterArrived>

</LanguageData>