<?xml version="1.0" encoding="UTF-8"?>
<LanguageData>
  
  <!-- EN: adult -->
  <AnimalAdult.label>成獣</AnimalAdult.label>
  
  <!-- EN: baby -->
  <AnimalBaby.label>幼児</AnimalBaby.label>
  
  <!-- EN: baby -->
  <AnimalBabyTiny.label>幼児</AnimalBabyTiny.label>
  
  <!-- EN: juvenile -->
  <AnimalJuvenile.label>幼獣</AnimalJuvenile.label>
  
  <!-- EN: adult -->
  <EusocialInsectAdult.label>成虫</EusocialInsectAdult.label>
  
  <!-- EN: immature -->
  <EusocialInsectJuvenile.label>幼虫</EusocialInsectJuvenile.label>
  
  <!-- EN: larva -->
  <EusocialInsectLarva.label>幼生</EusocialInsectLarva.label>
  
  <!-- EN: adult -->
  <HumanlikeAdult.label>大人</HumanlikeAdult.label>
  
  <!-- EN: baby -->
  <HumanlikeBaby.label>乳児</HumanlikeBaby.label>
  
  <!-- EN: child -->
  <HumanlikeChild.label>少年</HumanlikeChild.label>
  
  <!-- EN: teenager -->
  <HumanlikeTeenager.label>青年</HumanlikeTeenager.label>
  <!-- EN: teenage -->
  <HumanlikeTeenager.adjective>青年</HumanlikeTeenager.adjective>
  
  <!-- EN: toddler -->
  <HumanlikeToddler.label>幼児</HumanlikeToddler.label>
  
  <!-- EN: fully-formed -->
  <MechanoidFullyFormed.label>完全体</MechanoidFullyFormed.label>
  
</LanguageData>