<?xml version="1.0" encoding="utf-8" ?>
<LanguageData>

    <!-- Captured -->
	<rep>
		<path>Captured.rulePack.rulesStrings[0]</path>
		<trans>tale_noun->[prisoner_nameShortDef]の逮捕</trans>
	</rep>
	<rep>
		<path>Captured.rulePack.rulesStrings[1]</path>
		<trans>image->[capturer_nameFull]は、[circumstance_group]、[prisoner_nameFull]を捕まえている。</trans>
	</rep>
	<rep>
		<path>Captured.rulePack.rulesStrings[2]</path>
		<trans>image->[capturer_nameFull]は、[circumstance_group]、[prisoner_nameFull]の手を縛っている。</trans>
	</rep>
	<rep>
		<path>Captured.rulePack.rulesStrings[3]</path>
		<trans>image->[prisoner_objective]を奪っている間、[capturer_nameFull]をぴしゃりと手で打つ。</trans>
	</rep>
	<rep>
		<path>Captured.rulePack.rulesStrings[4]</path>
		<trans>circumstance_phrase->[prisoner_pronoun]はのたうちまわり</trans>
	</rep>
	<rep>
		<path>Captured.rulePack.rulesStrings[5]</path>
		<trans>circumstance_phrase->[prisoner_pronoun]は身をよじり</trans>
	</rep>
	<rep>
		<path>Captured.rulePack.rulesStrings[6]</path>
		<trans>circumstance_phrase->専門的な能力により</trans>
	</rep>
	<rep>
		<path>Captured.rulePack.rulesStrings[7]</path>
		<trans>circumstance_phrase->素人っぽい雑さで</trans>
	</rep>
	<rep>
		<path>Captured.rulePack.rulesStrings[8]</path>
		<trans>circumstance_phrase->明らかに度を超えた力で</trans>
	</rep>
	<rep>
		<path>Captured.rulePack.rulesStrings[9]</path>
		<trans>circumstance_phrase->喜んで</trans>
	</rep>
	<rep>
		<path>Captured.rulePack.rulesStrings[10]</path>
		<trans>circumstance_phrase->優越感に浸りながら</trans>
	</rep>
	<rep>
		<path>Captured.rulePack.rulesStrings[11]</path>
		<trans>desc_sentence->[capturer_nameShortDef]は、優越感に浸りながら [prisoner_nameShortDef]の眼を覗き込んでいる。</trans>
	</rep>
	<rep>
		<path>Captured.rulePack.rulesStrings[12]</path>
		<trans>desc_sentence->[prisoner_nameShortDef]は、怪我をして痛がっているようだ。</trans>
	</rep>
	<rep>
		<path>Captured.rulePack.rulesStrings[13]</path>
		<trans>desc_sentence->[prisoner_nameShortDef]は、[prisoner_possessive]巡り合わせにあきらめているよう。</trans>
	</rep>
	<rep>
		<path>Captured.rulePack.rulesStrings[14]</path>
		<trans>desc_sentence->[prisoner_nameShortDef]は、打ち負かされた怒りに歯を剥いている。</trans>
	</rep>
	<rep>
		<path>Captured.rulePack.rulesStrings[15]</path>
		<trans>desc_sentence->[capturer_nameShortDef]は、[prisoner_objective]を抑えるために、[prisoner_nameShortDef]をピシャリと打つ。</trans>
	</rep>
	<rep>
		<path>Captured.rulePack.rulesStrings[16]</path>
		<trans>desc_sentence->[capturer_nameShortDef]は、[prisoner_nameShortDef]の耳をひねりあげる。</trans>
	</rep>
	<rep>
		<path>Captured.rulePack.rulesStrings[17]</path>
		<trans>desc_sentence->[capturer_nameShortDef]は、手錠で[prisoner_nameShortDef]を押さえつける。</trans>
	</rep>
	<rep>
		<path>Captured.rulePack.rulesStrings[18]</path>
		<trans>desc_sentence->[capturer_nameShortDef]は、[prisoner_nameShortDef]の顔に唾を吐きかける。</trans>
	</rep>
	<rep>
		<path>Captured.rulePack.rulesStrings[19]</path>
		<trans>desc_sentence->[capturer_nameShortDef]は、[prisoner_nameShortDef]の眼に涙が湧き出るのを見て笑っている。</trans>
	</rep>
	<rep>
		<path>Captured.rulePack.rulesStrings[20]</path>
		<trans>desc_sentence->[capturer_nameShortDef]は、何か理由があるわけでもないのに[prisoner_nameShortDef]を蹴飛ばしている。</trans>
	</rep>


    <!-- Recruited -->
	<rep>
		<path>Recruited.rulePack.rulesStrings[0]</path>
        <trans>tale_noun->[joiner_nameShortDef]を勧誘</trans>
	</rep>
	<rep>
		<path>Recruited.rulePack.rulesStrings[1]</path>
		<trans>image->[recruiter_nameFull]は、[circumstance_group]、[joiner_nameFull]を勧誘している。</trans>
	</rep>
	<rep>
		<path>Recruited.rulePack.rulesStrings[2]</path>
		<trans>image->[recruiter_nameFull]は、[circumstance_group]、[joiner_nameFull]が、[joiner_pronoun]として入植者になることを歓迎している。</trans>
	</rep>
	<rep>
		<path>Recruited.rulePack.rulesStrings[3]</path>
        <trans>image->[recruiter_nameFull]は、[circumstance_group]、[joiner_nameFull]が納得のいくように話している。</trans>
	</rep>
	<rep>
		<path>Recruited.rulePack.rulesStrings[4]</path>
        <trans>circumstance_phrase->心暖かい握手をしながら</trans>
	</rep>
	<rep>
		<path>Recruited.rulePack.rulesStrings[5]</path>
        <trans>circumstance_phrase->皆に微笑みながら</trans>
	</rep>
	<rep>
		<path>Recruited.rulePack.rulesStrings[6]</path>
        <trans>circumstance_phrase->コロニー全体を前にして</trans>
	</rep>
	<rep>
		<path>Recruited.rulePack.rulesStrings[7]</path>
        <trans>circumstance_phrase->牢獄の中で</trans>
	</rep>
	<rep>
		<path>Recruited.rulePack.rulesStrings[8]</path>
		<trans>desc_sentence->[joiner_nameShortDef]は、了承してうなずいている。</trans>
	</rep>
	<rep>
		<path>Recruited.rulePack.rulesStrings[9]</path>
        <trans>desc_sentence->[joiner_nameShortDef]は、笑って、アイコンタクトをしている。</trans>
	</rep>
	<rep>
		<path>Recruited.rulePack.rulesStrings[10]</path>
        <trans>desc_sentence->[joiner_nameShortDef]は、ホッとしているよう。</trans>
	</rep>
	<rep>
		<path>Recruited.rulePack.rulesStrings[11]</path>
        <trans>desc_sentence->[joiner_nameShortDef]は、希望に満ちているよう。</trans>
	</rep>


    <!-- Hunted -->
	<rep>
		<path>Hunted.rulePack.rulesStrings[0]</path>
        <trans>tale_noun->[hunter_nameShortDef]の狩り</trans>
	</rep>
	<rep>
		<path>Hunted.rulePack.rulesStrings[1]</path>
        <trans>image->[prey_nameFull]は、[circumstance_group]、[hunter_nameFull]によって狩られる。 </trans>
	</rep>
	<rep>
		<path>Hunted.rulePack.rulesStrings[2]</path>
        <trans>image->[hunter_nameFull]は、[circumstance_group]、[prey_nameFull]に遠くからこっそりと忍び寄る。</trans>
	</rep>
	<rep>
		<path>Hunted.rulePack.rulesStrings[3]</path>
        <trans>image->[hunter_nameFull]は、[circumstance_group]、[prey_nameFull]を狩っている。</trans>
	</rep>
	<rep>
		<path>Hunted.rulePack.rulesStrings[4]</path>
        <trans>circumstance_phrase->[prey_nameShortDef]が気を緩めて隙に</trans>
	</rep>
	<rep>
		<path>Hunted.rulePack.rulesStrings[5]</path>
        <trans>circumstance_phrase->[prey_nameShortDef]が移動している隙に</trans>
	</rep>
	<rep>
		<path>Hunted.rulePack.rulesStrings[6]</path>
        <trans>circumstance_phrase->[prey_nameShortDef]が餌を食べている隙に</trans>
	</rep>
	<rep>
		<path>Hunted.rulePack.rulesStrings[7]</path>
        <trans>desc_sentence->[prey_nameShortDef]は、完全に忘れたかのようにみえる。</trans>
	</rep>
	<rep>
		<path>Hunted.rulePack.rulesStrings[8]</path>
        <trans>desc_sentence->[hunter_nameShortDef]は、[hunter_possessive] 武器をしっかりと握る。</trans>
	</rep>
	<rep>
		<path>Hunted.rulePack.rulesStrings[9]</path>
        <trans>desc_sentence->[prey_nameShortDef]は、何か変わったところは無いかと？、あたり一面に気を配っている。</trans>
	</rep>


    <!-- DidSurgery -->
	<rep>
		<path>DidSurgery.rulePack.rulesStrings[0]</path>
		<trans>tale_noun->[patient_nameShortDef]の外科手術</trans>
	</rep>
	<rep>
		<path>DidSurgery.rulePack.rulesStrings[1]</path>
		<trans>image->[surgeon_nameFull]は、[circumstance_group]、[patient_nameFull]を麻酔で眠らせている。</trans>
	</rep>
	<rep>
		<path>DidSurgery.rulePack.rulesStrings[2]</path>
		<trans>image->[surgeon_nameFull]は、[circumstance_group]、手術中に肘まで深く[patient_nameFull]の中に差し込んでいる。</trans>
	</rep>
	<rep>
		<path>DidSurgery.rulePack.rulesStrings[3]</path>
		<trans>image->[surgeon_nameFull]は、[circumstance_group]、手術中に[patient_nameFull]を切り刻んでいる。</trans>
	</rep>
	<rep>
		<path>DidSurgery.rulePack.rulesStrings[4]</path>
		<trans>circumstance_phrase->恐怖に震える[patient_pronoun]の</trans>
	</rep>
	<rep>
		<path>DidSurgery.rulePack.rulesStrings[5]</path>
		<trans>circumstance_phrase->[surgeon_nameShortDef]の足元に血だまりを作りながら</trans>
	</rep>
	<rep>
		<path>DidSurgery.rulePack.rulesStrings[6]</path>
		<trans>circumstance_phrase->見るも恐ろしい手術道具に囲まれている中で</trans>
	</rep>
	<rep>
		<path>DidSurgery.rulePack.rulesStrings[7]</path>
		<trans>circumstance_phrase->即席だが効果的なツールを使って</trans>
	</rep>
	<rep>
		<path>DidSurgery.rulePack.rulesStrings[8]</path>
		<trans>desc_sentence->[surgeon_nameShortDef]は、おびただしい汗をかいている。</trans>
	</rep>
	<rep>
		<path>DidSurgery.rulePack.rulesStrings[9]</path>
		<trans>desc_sentence->[surgeon_nameShortDef]は、信じられないほど、やるべき事に集中しているようにみえる。</trans>
	</rep>
	<rep>
		<path>DidSurgery.rulePack.rulesStrings[10]</path>
		<trans>desc_sentence->[surgeon_nameShortDef]は、[surgeon_possessive]顔に血のりをつけている。</trans>
	</rep>
	<rep>
		<path>DidSurgery.rulePack.rulesStrings[11]</path>
		<trans>desc_sentence->[patient_nameShortDef]は、首をふり、のたうちまわっている。</trans>
	</rep>

    <!-- ExecutedPrisoner -->
    <rep>
		<path>ExecutedPrisoner.rulePack.rulesStrings[  0]</path>
		<trans>tale_noun->[prisoner_nameShortDef]の処刑</trans>
	</rep>

    <rep>
		<path>ExecutedPrisoner.rulePack.rulesStrings[  1]</path>
		<trans>image->[warden_nameFull]は、[circumstance_group]、[prisoner_nameFull]を処刑している。 </trans>
	</rep>

    <rep>
		<path>ExecutedPrisoner.rulePack.rulesStrings[  2]</path>
		<trans>image->[warden_nameFull]は、[circumstance_group]、[prisoner_nameFull]を死の淵においやっている。</trans>
	</rep>

    <rep>
		<path>ExecutedPrisoner.rulePack.rulesStrings[  3]</path>
		<trans>image->[warden_nameFull]は、[circumstance_group]、[prisoner_nameFull]の処刑の準備をしている。</trans>
	</rep>

    <rep>
		<path>ExecutedPrisoner.rulePack.rulesStrings[  4]</path>
		<trans>image->[warden_nameFull]は、[circumstance_group]、牢獄に入り[prisoner_nameFull]を処刑するために連れ出している。</trans>
	</rep>

    <rep>
		<path>ExecutedPrisoner.rulePack.rulesStrings[  5]</path>
		<trans>circumstance_phrase->[prisoner_pronoun]は地面の上でのたうちまわっている中</trans>
	</rep>

    <rep>
		<path>ExecutedPrisoner.rulePack.rulesStrings[  6]</path>
		<trans>circumstance_phrase->[prisoner_pronoun]は、痛みに身をよじりながら</trans>
	</rep>

    <rep>
		<path>ExecutedPrisoner.rulePack.rulesStrings[  7]</path>
		<trans>circumstance_phrase->[prisoner_pronoun]は恐怖で叫んでいるなか</trans>
	</rep>

    <rep>
		<path>ExecutedPrisoner.rulePack.rulesStrings[  8]</path>
		<trans>circumstance_phrase->プロフェッショナルな手際の良さで</trans>
	</rep>

    <rep>
		<path>ExecutedPrisoner.rulePack.rulesStrings[  9]</path>
		<trans>circumstance_phrase->雑で、未熟ながらも</trans>
	</rep>

    <rep>
		<path>ExecutedPrisoner.rulePack.rulesStrings[ 10]</path>
		<trans>circumstance_phrase->明らかに必要以上の力で</trans>
	</rep>

    <rep>
		<path>ExecutedPrisoner.rulePack.rulesStrings[ 11]</path>
		<trans>circumstance_phrase->見るからに楽しそうに</trans>
	</rep>

    <rep>
		<path>ExecutedPrisoner.rulePack.rulesStrings[ 12]</path>
		<trans>circumstance_phrase->優越感に笑みを浮かべながら</trans>
	</rep>

    <rep>
		<path>ExecutedPrisoner.rulePack.rulesStrings[ 13]</path>
		<trans>circumstance_phrase->[warden_possessive]の眼には涙があふれて</trans>
	</rep>

    <rep>
		<path>ExecutedPrisoner.rulePack.rulesStrings[ 14]</path>
		<trans>circumstance_phrase->全くの無関心を装いつつ</trans>
	</rep>

    <rep>
		<path>ExecutedPrisoner.rulePack.rulesStrings[ 15]</path>
		<trans>circumstance_phrase->必要のない苦痛を与えている間</trans>
	</rep>

    <rep>
		<path>ExecutedPrisoner.rulePack.rulesStrings[ 16]</path>
		<trans>circumstance_phrase->何か別のことを考えながら</trans>
	</rep>

    <rep>
		<path>ExecutedPrisoner.rulePack.rulesStrings[ 17]</path>
		<trans>circumstance_phrase->とても良いことのように</trans>
	</rep>

    <rep>
		<path>ExecutedPrisoner.rulePack.rulesStrings[ 18]</path>
		<trans>desc_sentence->[warden_nameShortDef]は、過度に汗をかいている。</trans>
	</rep>

    <rep>
		<path>ExecutedPrisoner.rulePack.rulesStrings[ 19]</path>
		<trans>desc_sentence->[warden_nameShortDef]は、ほんのわずかヨダレをたらしている。</trans>
	</rep>

    <rep>
		<path>ExecutedPrisoner.rulePack.rulesStrings[ 20]</path>
		<trans>desc_sentence->[warden_nameShortDef]は、[warden_possessive]の顔に血のりをつけている。</trans>
	</rep>

    <rep>
		<path>ExecutedPrisoner.rulePack.rulesStrings[ 21]</path>
		<trans>desc_sentence->[prisoner_nameShortDef]は、首をふり、のたうちまわっている。</trans>
	</rep>

    <rep>
		<path>ExecutedPrisoner.rulePack.rulesStrings[ 22]</path>
		<trans>desc_sentence->[prisoner_nameShortDef]は、完全にあきらめたかのように見える。</trans>
	</rep>

    <rep>
		<path>ExecutedPrisoner.rulePack.rulesStrings[ 23]</path>
		<trans>desc_sentence->[prisoner_nameShortDef]は、[prisoner_possessive]の眼を閉じて、神に祈っているようにみえる。</trans>
	</rep>

    <rep>
		<path>ExecutedPrisoner.rulePack.rulesStrings[ 24]</path>
		<trans>desc_sentence->[prisoner_nameShortDef]は、反抗的に見える。</trans>
	</rep>


    <!-- KidnappedColonist -->
    <rep>
		<path>KidnappedColonist.rulePack.rulesStrings[  0]</path>
		<trans>tale_noun->[victim_nameShortDef]が連れ去られる</trans>
	</rep>

    <rep>
		<path>KidnappedColonist.rulePack.rulesStrings[  1]</path>
		<trans>image->[kidnapper_nameFull]は、[circumstance_group]、[victim_nameFull]を、[kidnapper_factionName]に連れ去る。</trans>
	</rep>

    <rep>
		<path>KidnappedColonist.rulePack.rulesStrings[  2]</path>
		<trans>image->[kidnapper_factionName]の[kidnapper_nameFull]は、[circumstance_group]、[victim_nameFull]を誘拐する。</trans>
	</rep>

    <rep>
		<path>KidnappedColonist.rulePack.rulesStrings[  3]</path>
		<trans>image->[kidnapper_nameFull]は、[circumstance_group]、[victim_nameFull]を誘拐する。 </trans>
	</rep>

    <rep>
		<path>KidnappedColonist.rulePack.rulesStrings[  4]</path>
		<trans>circumstance_phrase->[victim_pronoun]は、痛みに身をよじりながら</trans>
	</rep>

    <rep>
		<path>KidnappedColonist.rulePack.rulesStrings[  5]</path>
		<trans>circumstance_phrase->プロフェッショナルな手際の良さで</trans>
	</rep>

    <rep>
		<path>KidnappedColonist.rulePack.rulesStrings[  6]</path>
		<trans>circumstance_phrase->素人っぽい雑さで</trans>
	</rep>

    <rep>
		<path>KidnappedColonist.rulePack.rulesStrings[  7]</path>
		<trans>circumstance_phrase->明らかに必要以上の力で</trans>
	</rep>

    <rep>
		<path>KidnappedColonist.rulePack.rulesStrings[  8]</path>
		<trans>circumstance_phrase->喜んで</trans>
	</rep>

    <rep>
		<path>KidnappedColonist.rulePack.rulesStrings[  9]</path>
		<trans>circumstance_phrase->優越感に浸りながら</trans>
	</rep>

    <rep>
		<path>KidnappedColonist.rulePack.rulesStrings[ 10]</path>
		<trans>circumstance_phrase->血と泥にまみれながら</trans>
	</rep>

    <rep>
		<path>KidnappedColonist.rulePack.rulesStrings[ 11]</path>
		<trans>desc_sentence->[kidnapper_nameShortDef]は、完全にあきらめたかのように見える。</trans>
	</rep>

    <rep>
		<path>KidnappedColonist.rulePack.rulesStrings[ 12]</path>
		<trans>desc_sentence->[victim_nameShortDef]は、[prisoner_possessive]の眼を閉じて、神に祈っているようにみえる。</trans>
	</rep>

    <rep>
		<path>KidnappedColonist.rulePack.rulesStrings[ 13]</path>
		<trans>desc_sentence->[victim_nameShortDef]は、反抗的に見える。</trans>
	</rep>

    <rep>
		<path>KidnappedColonist.rulePack.rulesStrings[ 14]</path>
		<trans>desc_sentence->[victim_nameShortDef]は、怒りと恐怖で叫んでいる。</trans>
	</rep>

    <rep>
		<path>KidnappedColonist.rulePack.rulesStrings[ 15]</path>
		<trans>desc_sentence->[victim_nameShortDef]は、精魂尽き果てたかのようにみえる。</trans>
	</rep>

    <rep>
		<path>KidnappedColonist.rulePack.rulesStrings[ 16]</path>
		<trans>desc_sentence->[victim_nameShortDef]は、ひどい怪我を負ったようにみえる。</trans>
	</rep>


    <!-- TamedAnimal -->
    <rep>
		<path>TamedAnimal.rulePack.rulesStrings[  0]</path>
		<trans>tale_noun->[human_nameShortDef]が飼い慣らす、[animal_nameShortDef]たち</trans>
	</rep>

    <rep>
		<path>TamedAnimal.rulePack.rulesStrings[  1]</path>
		<trans>image->[human_nameFull]は、[circumstance_group]、[animal_nameFull]を飼い慣らす。</trans>
	</rep>

    <rep>
		<path>TamedAnimal.rulePack.rulesStrings[  2]</path>
		<trans>image->[human_nameFull]は、[circumstance_group]、[animal_nameFull]にご馳走を与えている。</trans>
	</rep>

    <rep>
		<path>TamedAnimal.rulePack.rulesStrings[  3]</path>
		<trans>image->[human_nameFull]は、[circumstance_group]、驚きやすい[animal_nameFull]に小声で話しかける。</trans>
	</rep>

    <rep>
		<path>TamedAnimal.rulePack.rulesStrings[  4]</path>
		<trans>image->[human_nameFull]は、[circumstance_group]、野性の[animal_nameFull]をなだめている。</trans>
	</rep>

    <rep>
		<path>TamedAnimal.rulePack.rulesStrings[  5]</path>
		<trans>circumstance_phrase->最大限の注意と世話を払いつつ</trans>
	</rep>

    <rep>
		<path>TamedAnimal.rulePack.rulesStrings[  6]</path>
		<trans>circumstance_phrase->笑顔と共に</trans>
	</rep>

    <rep>
		<path>TamedAnimal.rulePack.rulesStrings[  7]</path>
		<trans>circumstance_phrase->疲れ果てながらも、幸せで</trans>
	</rep>

    <rep>
		<path>TamedAnimal.rulePack.rulesStrings[  8]</path>
		<trans>desc_sentence->[animal_nameShortDef]は、攻撃的に歯を剥いてくる。</trans>
	</rep>

    <rep>
		<path>TamedAnimal.rulePack.rulesStrings[  9]</path>
		<trans>desc_sentence->[animal_nameShortDef]は恋の美酒に酔いしれて眠そうにみえる。</trans>
	</rep>

    <rep>
		<path>TamedAnimal.rulePack.rulesStrings[ 10]</path>
		<trans>desc_sentence->[animal_nameShortDef]は、暗示の効果が現れてきたように見える。</trans>
	</rep>

    <rep>
		<path>TamedAnimal.rulePack.rulesStrings[ 11]</path>
		<trans>desc_sentence->[animal_nameShortDef]は、怖がりつつも興味を示しているように見える。</trans>
	</rep>

    <rep>
		<path>TamedAnimal.rulePack.rulesStrings[ 12]</path>
		<trans>desc_sentence->[animal_nameShortDef]の心を魅了したように見える。</trans>
	</rep>

    <rep>
		<path>TamedAnimal.rulePack.rulesStrings[ 13]</path>
		<trans>desc_sentence->[human_nameShortDef]は、[animal_nameShortDef]に、力強い愛情を伝えている。</trans>
	</rep>

    <!-- KilledBy -->
        <!-- note that killer may not be filled in, so this has to be resolvable without any killer_ symbols -->
    <rep>
		<path>KilledBy.rulePack.rulesStrings[  0]</path>
		<trans>tale_noun->[killer_nameShortDef]による、[victim_nameShortDef]殺し</trans>
	</rep>

    <rep>
		<path>KilledBy.rulePack.rulesStrings[  1]</path>
		<trans>tale_noun->[victim_nameShortDef]が、[killer_nameShortDef]によって殺された</trans>
	</rep>

    <rep>
		<path>KilledBy.rulePack.rulesStrings[  2]</path>
		<trans>tale_noun->[victim_nameShortDef]が殺された</trans>
	</rep>

    <rep>
		<path>KilledBy.rulePack.rulesStrings[  3]</path>
		<trans>image->[victim_nameFull]は、[circumstance_group]、[killer_nameFull]に殺された。 </trans>
	</rep>

    <rep>
		<path>KilledBy.rulePack.rulesStrings[  4]</path>
		<trans>image->[killer_nameFull]は、[circumstance_group]、[victim_nameFull]を殺す。</trans>
	</rep>

    <rep>
		<path>KilledBy.rulePack.rulesStrings[  5]</path>
		<trans>image->[killer_nameFull]は、[circumstance_group]、[victim_nameFull]の人生を終わらせる。</trans>
	</rep>

    <rep>
		<path>KilledBy.rulePack.rulesStrings[  6]</path>
		<trans>image->[killer_nameFull]は、[circumstance_group]、残忍に[victim_nameFull]を殺す。</trans>
	</rep>

    <rep>
		<path>KilledBy.rulePack.rulesStrings[  7]</path>
		<trans>image->[victim_nameFull]は、[circumstance_group]、殺された。</trans>
	</rep>

    <rep>
		<path>KilledBy.rulePack.rulesStrings[  8]</path>
		<trans>circumstance_phrase->一見したところ無慈悲に</trans>
	</rep>

    <rep>
		<path>KilledBy.rulePack.rulesStrings[  9]</path>
		<trans>circumstance_phrase->冷酷に</trans>
	</rep>

    <rep>
		<path>KilledBy.rulePack.rulesStrings[ 10]</path>
		<trans>circumstance_phrase->激しい怒りと共に</trans>
	</rep>

    <rep>
		<path>KilledBy.rulePack.rulesStrings[ 11]</path>
		<trans>circumstance_phrase->素早く、無駄の無い動きで</trans>
	</rep>

    <rep>
		<path>KilledBy.rulePack.rulesStrings[ 12]</path>
		<trans>circumstance_phrase->感情を表に出さずに</trans>
	</rep>

    <rep>
		<path>KilledBy.rulePack.rulesStrings[ 13]</path>
		<trans>circumstance_phrase->希望も無しに</trans>
	</rep>

    <rep>
		<path>KilledBy.rulePack.rulesStrings[ 14]</path>
		<trans>circumstance_phrase->卑劣で、冷淡な方法で</trans>
	</rep>

    <rep>
		<path>KilledBy.rulePack.rulesStrings[ 15]</path>
		<trans>desc_sentence->The sun is setting behind them in a symbolic echo of the event.</trans>
	</rep>

    <rep>
		<path>KilledBy.rulePack.rulesStrings[ 16]</path>
		<trans>desc_sentence->[quantity_adjphrase] [animal]が、傍らでみている。</trans>
	</rep>

    <rep>
		<path>KilledBy.rulePack.rulesStrings[ 17]</path>
		<trans>desc_sentence->[side_position]の A [outlander] watches silently .</trans>
	</rep>

    <rep>
		<path>KilledBy.rulePack.rulesStrings[ 18]</path>
		<trans>desc_sentence->[victim_nameShortDef]の周りに血だまりができている。</trans>
	</rep>

    <rep>
		<path>KilledBy.rulePack.rulesStrings[ 19]</path>
		<trans>desc_sentence->[victim_nameShortDef]の眼は、現実的に死んだようにみえる。</trans>
	</rep>

    <rep>
		<path>KilledBy.rulePack.rulesStrings[ 20]</path>
		<trans>desc_sentence->[killer_nameShortDef]は、[killer_possessive]歯を剥き出しにしている。</trans>
	</rep>

    <rep>
		<path>KilledBy.rulePack.rulesStrings[ 21]</path>
		<trans>desc_sentence->[killer_nameShortDef]は満ち足りたように見える。</trans>
	</rep>

    <rep>
		<path>KilledBy.rulePack.rulesStrings[ 22]</path>
		<trans>desc_sentence->[killer_nameShortDef]は、[killer_pronoun]がしたことを悩んでいる。</trans>
	</rep>

    <rep>
		<path>KilledBy.rulePack.rulesStrings[ 23]</path>
		<trans>desc_sentence->[killer_nameShortDef]は、この状況に満足しているようだ。</trans>
	</rep>

    <rep>
		<path>KilledBy.rulePack.rulesStrings[ 24]</path>
		<trans>desc_sentence->[killer_nameShortDef]は、得意になっているようだ。</trans>
	</rep>

    <!-- SoldPrisoner -->
    <rep>
		<path>SoldPrisoner.rulePack.rulesStrings[  0]</path>
		<trans>tale_noun->[prisoner_nameShortDef]がトレーダーに売られた</trans>
	</rep>

    <rep>
		<path>SoldPrisoner.rulePack.rulesStrings[  1]</path>
		<trans>image->[trader_nameFull]は、[circumstance_group]、[prisoner_nameFull]を、[seller_nameFull]から買った。</trans>
	</rep>

    <rep>
		<path>SoldPrisoner.rulePack.rulesStrings[  2]</path>
		<trans>image->[seller_nameFull]は、[circumstance_group] 、[prisoner_nameFull]を、[seller_nameFull]に売る。</trans>
	</rep>

    <rep>
		<path>SoldPrisoner.rulePack.rulesStrings[  3]</path>
		<trans>circumstance_phrase->他の入植者が非難しているなか</trans>
	</rep>

    <rep>
		<path>SoldPrisoner.rulePack.rulesStrings[  4]</path>
		<trans>circumstance_phrase->[seller_nameShortDef]が、[trader_possessive]金を数えている間</trans>
	</rep>

    <rep>
		<path>SoldPrisoner.rulePack.rulesStrings[  5]</path>
		<trans>circumstance_phrase->[prisoner_nameShortDef]が悲しげな唸り声をあげているなか</trans>
	</rep>

    <rep>
		<path>SoldPrisoner.rulePack.rulesStrings[  6]</path>
		<trans>circumstance_phrase->[prisoner_nameShortDef]の無念の声に</trans>
	</rep>

    <rep>
		<path>SoldPrisoner.rulePack.rulesStrings[  7]</path>
		<trans>desc_sentence->[trader_nameShortDef]は、悪魔の微笑みを浮かべている。</trans>
	</rep>

    <rep>
		<path>SoldPrisoner.rulePack.rulesStrings[  8]</path>
		<trans>desc_sentence->[seller_nameShortDef]は、マニアックに笑っている。</trans>
	</rep>

    <rep>
		<path>SoldPrisoner.rulePack.rulesStrings[  9]</path>
		<trans>desc_sentence->[seller_nameShortDef]は、しぶしぶ[prisoner_nameShortDef]の手を、トレーダーに渡す。</trans>
	</rep>

    <rep>
		<path>SoldPrisoner.rulePack.rulesStrings[ 10]</path>
		<trans>desc_sentence->[prisoner_nameShortDef]は、反抗的な目で[prisoner_possessive]新しい主人を見る。</trans>
	</rep>

    <rep>
		<path>SoldPrisoner.rulePack.rulesStrings[ 11]</path>
		<trans>desc_sentence->[trader_nameShortDef]は、[prisoner_possessive]の鎖で[prisoner_nameShortDef]をしょぴく。</trans>
	</rep>

    <rep>
		<path>SoldPrisoner.rulePack.rulesStrings[ 12]</path>
		<trans>desc_sentence->[prisoner_nameShortDef] stares at [seller_nameShortDef], plotting [prisoner_possessive] revenge.</trans>
	</rep>

    <rep>
		<path>SoldPrisoner.rulePack.rulesStrings[ 13]</path>
		<trans>desc_sentence->[prisoner_nameShortDef]は、泣いている。</trans>
	</rep>

    <rep>
		<path>SoldPrisoner.rulePack.rulesStrings[ 14]</path>
		<trans>desc_sentence->[prisoner_nameShortDef]は、[seller_nameShortDef]の顔に唾を吐きかけた。</trans>
	</rep>

    <rep>
		<path>SoldPrisoner.rulePack.rulesStrings[ 15]</path>
		<trans>desc_sentence->[Prisoner_nameShortDef]は、地面に倒れ伏した。</trans>
	</rep>

    <rep>
		<path>SoldPrisoner.rulePack.rulesStrings[ 16]</path>
		<trans>desc_sentence->[Seller_nameShortDef]は、[prisoner_nameShortDef]をつなぐ鎖を、[trader_nameShortDef]の手に素早く押しやる。</trans>
	</rep>

    <rep>
		<path>SoldPrisoner.rulePack.rulesStrings[ 17]</path>
		<trans>desc_sentence->絶望の空気があたりに充満する。</trans>
	</rep>


    <!-- TrainedAnimal -->
    <rep>
		<path>TrainedAnimal.rulePack.rulesStrings[  0]</path>
		<trans>tale_noun->[animal_nameShortDef]の調教</trans>
	</rep>

    <rep>
		<path>TrainedAnimal.rulePack.rulesStrings[  1]</path>
		<trans>image->[human_nameFull]は、[circumstance_group]、[animal_nameFull]に[trainable_label]を[train_syn]する。</trans>
	</rep>

    <rep>
		<path>TrainedAnimal.rulePack.rulesStrings[  2]</path>
		<trans>image->[human_nameFull]は、[circumstance_group]、[animal_nameFull]に[trainable_label]を教える。</trans>
	</rep>

    <rep>
		<path>TrainedAnimal.rulePack.rulesStrings[  3]</path>
		<trans>image->[human_nameFull]、[circumstance_group]、[animal_nameFull]と[trainable_label]を練習する。</trans>
	</rep>

    <rep>
		<path>TrainedAnimal.rulePack.rulesStrings[  4]</path>
		<trans>train_syn->調教</trans>
	</rep>

    <rep>
		<path>TrainedAnimal.rulePack.rulesStrings[  5]</path>
		<trans>train_syn->訓練</trans>
	</rep>

    <rep>
		<path>TrainedAnimal.rulePack.rulesStrings[  6]</path>
		<trans>train_syn->指導</trans>
	</rep>

    <rep>
		<path>TrainedAnimal.rulePack.rulesStrings[  7]</path>
		<trans>train_syn->教え込みを</trans>
	</rep>

    <rep>
		<path>TrainedAnimal.rulePack.rulesStrings[  8]</path>
		<trans>train_syn->教育</trans>
	</rep>

    <rep>
		<path>TrainedAnimal.rulePack.rulesStrings[  9]</path>
		<trans>circumstance_phrase->彼を観察しながら</trans>
	</rep>

    <rep>
		<path>TrainedAnimal.rulePack.rulesStrings[ 10]</path>
		<trans>circumstance_phrase->野性の[animal]の観察をうんざりしながら</trans>
	</rep>

    <rep>
		<path>TrainedAnimal.rulePack.rulesStrings[ 11]</path>
		<trans>circumstance_phrase->[animal_pronoun]が野獣だったころの、[animal_nameShortDef]のシンプルな日々のことを考えながら</trans>
	</rep>

    <rep>
		<path>TrainedAnimal.rulePack.rulesStrings[ 12]</path>
		<trans>circumstance_phrase->[human_nameShortDef]は、今日のランチのことに気を取られながら</trans>
	</rep>

    <rep>
		<path>TrainedAnimal.rulePack.rulesStrings[ 13]</path>
		<trans>circumstance_phrase->他の入植者は、何をしているんだろうと気をとられながら</trans>
	</rep>

    <rep>
		<path>TrainedAnimal.rulePack.rulesStrings[ 14]</path>
		<trans>desc_sentence->[human_nameShortDef]、喜びを表にだしている。</trans>
	</rep>

    <rep>
		<path>TrainedAnimal.rulePack.rulesStrings[ 15]</path>
		<trans>desc_sentence->[human_nameShortDef]は、微笑んでいる。</trans>
	</rep>

    <rep>
		<path>TrainedAnimal.rulePack.rulesStrings[ 16]</path>
		<trans>desc_sentence->[human_nameShortDef]は、うんざりして飽きている。</trans>
	</rep>

    <rep>
		<path>TrainedAnimal.rulePack.rulesStrings[ 17]</path>
		<trans>desc_sentence->[human_nameShortDef]は、[human_possessive]拳を脅迫的に振り回している。</trans>
	</rep>

    <rep>
		<path>TrainedAnimal.rulePack.rulesStrings[ 18]</path>
		<trans>desc_sentence->[human_nameShortDef]は、[human_possessive]眉にシワを寄せて集中している。</trans>
	</rep>

    <rep>
		<path>TrainedAnimal.rulePack.rulesStrings[ 19]</path>
		<trans>desc_sentence->[animal_nameShortDef]は、困惑しているようだ。</trans>
	</rep>

    <rep>
		<path>TrainedAnimal.rulePack.rulesStrings[ 20]</path>
		<trans>desc_sentence->[animal_nameShortDef]は、[animal_possessive] 口に武器を咥えている。</trans>
	</rep>

    <rep>
		<path>TrainedAnimal.rulePack.rulesStrings[ 21]</path>
		<trans>desc_sentence->[animal_nameShortDef]は、唸り声をあげている。</trans>
	</rep>

    <rep>
		<path>TrainedAnimal.rulePack.rulesStrings[ 22]</path>
		<trans>desc_sentence->[human_nameShortDef]は、欲求不満がたまって[human_possessive] 頭を振っている。</trans>
	</rep>

    <rep>
		<path>TrainedAnimal.rulePack.rulesStrings[ 23]</path>
		<trans>desc_sentence->[animal_nameShortDef]は、恐怖に震えている。</trans>
	</rep>

    <rep>
		<path>TrainedAnimal.rulePack.rulesStrings[ 24]</path>
		<trans>desc_sentence->[animal_nameShortDef]は、 appears to be morphing into a [vegetable].</trans>
	</rep>

    <rep>
		<path>TrainedAnimal.rulePack.rulesStrings[ 25]</path>
		<trans>desc_sentence->[animal_nameShortDef]は、有能な財産となっている。</trans>
	</rep>

    <rep>
		<path>TrainedAnimal.rulePack.rulesStrings[ 26]</path>
		<trans>desc_sentence->[animal_nameShortDef]は、[color]と[color]の2色からなっている。</trans>
	</rep>

    <rep>
		<path>TrainedAnimal.rulePack.rulesStrings[ 27]</path>
		<trans>desc_sentence->[animal_nameShortDef]は鱗に被われている。</trans>
	</rep>

    <rep>
		<path>TrainedAnimal.rulePack.rulesStrings[ 28]</path>
		<trans>desc_sentence->[human_nameShortDef]は、[quantity]腕で表現している。</trans>
	</rep>

    <rep>
		<path>TrainedAnimal.rulePack.rulesStrings[ 29]</path>
		<trans>desc_sentence->[human_nameShortDef] is morphing into [animal_ShortDefinite].</trans>
	</rep>

</LanguageData>
