<?xml version="1.0" encoding="utf-8" ?>
<LanguageData>

	<Plant_Dandelion.label>タンポポ</Plant_Dandelion.label>
	<Plant_Dandelion.description>小さな黄色い花で,大きな群生をつくります.よく雑草と思われがちですが,満開のタンポポは本当に美しいです.</Plant_Dandelion.description>

	<Plant_Astragalus.label>レンゲソウ</Plant_Astragalus.label>
	<Plant_Astragalus.description>小さな多年性の野生の高山植物です.</Plant_Astragalus.description>

	<Plant_Moss.label>コケ</Plant_Moss.label>
	<Plant_Moss.description>弱い光と気温が低い所で繁茂する野生のコケです.コケは伸びるのに非常に時間がかかりますが霜耐性があります.</Plant_Moss.description>

    <!--===========================  Wild - clustering bushes (some harvestable) ==============================-->
    <Plant_Berry.label>野苺</Plant_Berry.label>
    <Plant_Berry.description>毛がフサフサした野生植物です.おいしい赤いベリーができます.ベリーは調理しても,もちろん生食でも食べられます.</Plant_Berry.description>

    <!--============================ Wild - Trees ============================-->
	<Plant_TreeOak.label>オーク</Plant_TreeOak.label>
	<Plant_TreeOak.description>強くて硬い木,成長が遅い分,その木は強くなります.多くの文化において "オーク"は強さを表す隠喩として使われています.</Plant_TreeOak.description>

	<Plant_TreePoplar.label>ポプラ</Plant_TreePoplar.label>
	<Plant_TreePoplar.description>柔らかい木,成長はとても早いです.あいにく,この木は弱いので,素材として硬い木よりも使い道が少なくなります.</Plant_TreePoplar.description>

	<Plant_TreePine.label>松</Plant_TreePine.label>
	<Plant_TreePine.description>トゲの多い松ぼっくりに覆われた大きな針葉樹です.独特な円錐状の形に成長します.</Plant_TreePine.description>

	<Plant_TreeBirch.label>シラカバ</Plant_TreeBirch.label>
	<Plant_TreeBirch.description>細く,白色,紙のような樹皮で知られる温暖気候の木です.</Plant_TreeBirch.description>

</LanguageData>