<?xml version="1.0" encoding="utf-8" ?>
<LanguageData>

	<Deer.label>シカ</Deer.label>
	<Deer.description>中型の草食動物、一般的に彼らの邪魔をしない限り平和的です。</Deer.description>

	<Squirrel.label>リス</Squirrel.label>
	<Squirrel.description>人の行くところは、どこにでも姿を表します。 多くの丈夫で用途の広い齧歯類のうちのひとつです。</Squirrel.description>

	<Elk.label>ヘラジカ</Elk.label>
	<Elk.description>大きなシカ科の生き物。寒冷な気候に適応しています。</Elk.description>

	<Alphabeaver.label>アルファビーバー</Alphabeaver.label>
	<Alphabeaver.description>機械のような効率で木を集めるために、遺伝子操作によってビーバーから派生させた大きな生き物。彼ら専用の飼料が欠乏したとき、木全体を食べてしまう躁状態になります。</Alphabeaver.description>

	<WildBoar.label>イノシシ</WildBoar.label>
	<WildBoar.description>いくつかの文化によっては不潔であると考えられていました、この家族的な毛むくじゃらなブタの祖先は、 その肉の独特の風味が珍重されます。</WildBoar.description>

	<Boomrat.label>ボムネズミ</Boomrat.label>
	<Boomrat.description>慎重な遺伝子操作による武器化であったとしても、又は一風変わった防御機構だとしても、この齧歯類のような生き物は、死ぬ間際に強烈な爆発を起こします。</Boomrat.description>

	<Hare.label>ノウサギ </Hare.label>
	<Hare.description>この小さな孤独な生き物は、危険からぴょんぴょん跳んで離れていきます。</Hare.description>

	<Tortoise.label>カメ</Tortoise.label>
	<Tortoise.description>この硬い甲羅で覆われた爬虫類は、歩く速度がとても遅い反面、びっくりするぐらい 素早く噛むことで知られています。</Tortoise.description>

    <Thrumbo.label>スランボ</Thrumbo.label>
    <Thrumbo.description>出所不明な超巨大生物。本来 スランボ はおとなしいですが、起こらせると極めて危険です。その長い毛皮は群を抜いて美しく貴重でなうえ、非常に鋭い角は、ほとんどのマーケットで値がつけられません。 伝説によると、年老いた thrumbo は全宇宙の中で、もっとも賢い生物とされていますが、言葉で話すことはしません。</Thrumbo.description>

</LanguageData>