<?xml version="1.0" encoding="utf-8" ?>
<LanguageData>

    <AridShrubland.label>サバンナ</AridShrubland.label>
    <AridShrubland.description>A dry region, but not dry enough to become a true desert. Open plains with grasses and bushes give way to scattered groves of trees. Plants are hardy and there is a moderate density of animals, but arable soil is hard to find.</AridShrubland.description>

    <Desert.label>砂漠</Desert.label>
    <Desert.description>A very dry area which supports little life. There is very little arable land, and animal life is very sparse. Deserts can be hot, or quite cold.</Desert.description>

    <ExtremeDesert.label>極限の砂漠</ExtremeDesert.label>
    <ExtremeDesert.description>An extremely hot, dry area, devoid of almost all life. Searing heat and a near total lack of arable land make it very difficult to survive here.</ExtremeDesert.description>

</LanguageData>