<?xml version="1.0" encoding="UTF-8"?>
<LanguageData>
  
  <!-- EN: boomalope -->
  <Boomalope.label>ボマロープ</Boomalope.label>
  <!-- EN: boomalope calf -->
  <Boomalope.lifeStages.boomalope_calf.label>子ボマロープ</Boomalope.lifeStages.boomalope_calf.label>
  <!-- EN: boomalope calves -->
  <Boomalope.lifeStages.boomalope_calf.labelPlural>子ボマロープ</Boomalope.lifeStages.boomalope_calf.labelPlural>
  
  <!-- EN: cobra -->
  <Cobra.label>コブラ</Cobra.label>
  
  <!-- EN: monkey -->
  <Monkey.label>サル</Monkey.label>
  
</LanguageData>