<?xml version="1.0" encoding="utf-8" ?>
<LanguageData>

    <Impressiveness.label>見栄え</Impressiveness.label>
    <Impressiveness.scoreStages.awful.label>極度に悪い</Impressiveness.scoreStages.awful.label>
    <Impressiveness.scoreStages.dull.label>味気ない</Impressiveness.scoreStages.dull.label>
    <Impressiveness.scoreStages.mediocre.label>平凡</Impressiveness.scoreStages.mediocre.label>
    <Impressiveness.scoreStages.decent.label>見苦しくない</Impressiveness.scoreStages.decent.label>
    <Impressiveness.scoreStages.slightly_impressive.label>わずかに印象的</Impressiveness.scoreStages.slightly_impressive.label>
    <Impressiveness.scoreStages.somewhat_impressive.label>いくぶん印象的</Impressiveness.scoreStages.somewhat_impressive.label>
    <Impressiveness.scoreStages.very_impressive.label>とても印象的</Impressiveness.scoreStages.very_impressive.label>
    <Impressiveness.scoreStages.extremely_impressive.label>非常に印象的</Impressiveness.scoreStages.extremely_impressive.label>
    <Impressiveness.scoreStages.unbelievably_impressive.label>信じられないほど印象的</Impressiveness.scoreStages.unbelievably_impressive.label>
    <Impressiveness.scoreStages.wondrously_impressive.label>驚くほど素晴らしい</Impressiveness.scoreStages.wondrously_impressive.label>

    <Wealth.label>富</Wealth.label>
    <Wealth.scoreStages.impoverished.label>貧しい</Wealth.scoreStages.impoverished.label>
    <Wealth.scoreStages.somewhat_poor.label>やや貧しい</Wealth.scoreStages.somewhat_poor.label>
    <Wealth.scoreStages.mediocre.label>良くも悪くもない</Wealth.scoreStages.mediocre.label>
    <Wealth.scoreStages.somewhat_rich.label>やや裕福</Wealth.scoreStages.somewhat_rich.label>
    <Wealth.scoreStages.rich.label>裕福</Wealth.scoreStages.rich.label>
    <Wealth.scoreStages.luxurious.label>贅沢</Wealth.scoreStages.luxurious.label>
    <Wealth.scoreStages.very_luxurious.label>とても贅沢</Wealth.scoreStages.very_luxurious.label>
    <Wealth.scoreStages.extremely_luxurious.label>非常に贅沢</Wealth.scoreStages.extremely_luxurious.label>
    <Wealth.scoreStages.unbelievably_luxurious.label>信じられないほど贅沢</Wealth.scoreStages.unbelievably_luxurious.label>

    <Space.label>広さ</Space.label>
    <Space.scoreStages.cramped.label>窮屈</Space.scoreStages.cramped.label>
    <Space.scoreStages.rather_tight.label>やや窮屈</Space.scoreStages.rather_tight.label>
    <Space.scoreStages.averagesized.label>平均的な広さ</Space.scoreStages.averagesized.label>
    <Space.scoreStages.somewhat_spacious.label>やや広々</Space.scoreStages.somewhat_spacious.label>
    <Space.scoreStages.quite_spacious.label>広々</Space.scoreStages.quite_spacious.label>
    <Space.scoreStages.very_spacious.label>とても広々</Space.scoreStages.very_spacious.label>
    <Space.scoreStages.extremely_spacious.label>非常に広々</Space.scoreStages.extremely_spacious.label>

    <Beauty.label>美しさ</Beauty.label>
    <Beauty.scoreStages.hideous.label>ひどく醜い</Beauty.scoreStages.hideous.label>
    <Beauty.scoreStages.ugly.label>醜い</Beauty.scoreStages.ugly.label>
    <Beauty.scoreStages.neutral.label>並</Beauty.scoreStages.neutral.label>
    <Beauty.scoreStages.pretty.label>やや魅力的</Beauty.scoreStages.pretty.label>
    <Beauty.scoreStages.beautiful.label>美しい</Beauty.scoreStages.beautiful.label>
    <Beauty.scoreStages.very_beautiful.label>とても美しい</Beauty.scoreStages.very_beautiful.label>
    <Beauty.scoreStages.extremely_beautiful.label>非常に美しい</Beauty.scoreStages.extremely_beautiful.label>
    <Beauty.scoreStages.unbelievably_beautiful.label>信じられないほど美しい</Beauty.scoreStages.unbelievably_beautiful.label>

    <Cleanliness.label>清潔さ</Cleanliness.label>
    <Cleanliness.scoreStages.very_dirty.label>とても汚い</Cleanliness.scoreStages.very_dirty.label>
    <Cleanliness.scoreStages.dirty.label>汚い</Cleanliness.scoreStages.dirty.label>
    <Cleanliness.scoreStages.slightly_dirty.label>少し汚い</Cleanliness.scoreStages.slightly_dirty.label>
    <Cleanliness.scoreStages.clean.label>清潔</Cleanliness.scoreStages.clean.label>
    <Cleanliness.scoreStages.sterile.label>無菌</Cleanliness.scoreStages.sterile.label>

    <InfectionChanceFactor.label>感染率</InfectionChanceFactor.label>
    <SurgerySuccessChanceCleanlinessFactor.label>外科手術成功に掛ける清潔度</SurgerySuccessChanceCleanlinessFactor.label>
    <ResearchSpeedFactor.label>研究速度倍率</ResearchSpeedFactor.label>
    <FoodPoisonChance.label>食中毒発生率</FoodPoisonChance.label>
    <GraveVisitingJoyGainFactor.label>やすらぎ効果倍率</GraveVisitingJoyGainFactor.label>

</LanguageData>